{
  "access": "premium",
  "author": null,
  "companies": [],
  "created": 1682726400,
  "difficulty": "easy",
  "duration": 10,
  "featured": false,
  "format": "javascript",
  "frameworkDefault": null,
  "frameworks": [],
  "href": "/questions/javascript/find-last-index",
  "importance": "low",
  "languages": [
    "js",
    "ts"
  ],
  "nextQuestions": [],
  "published": true,
  "ranking": 100,
  "similarQuestions": [
    "find-index"
  ],
  "slug": "find-last-index",
  "subtitle": null,
  "topics": []
}