{
  "AE": {
    "conversionFactor": 0.55,
    "country": {
      "code": "AE",
      "name": "United Arab Emirates"
    },
    "currency": {
      "code": "aed",
      "exchangeRate": 3.6727,
      "symbol": "د.إ"
    }
  },
  "AF": {
    "conversionFactor": 0.25,
    "country": {
      "code": "AF",
      "name": "Afghanistan"
    },
    "currency": {
      "code": "afn",
      "exchangeRate": 86.726892,
      "symbol": "؋"
    }
  },
  "AG": {
    "conversionFactor": 0.75,
    "country": {
      "code": "AG",
      "name": "Antigua and Barbuda"
    },
    "currency": {
      "code": "xcd",
      "exchangeRate": 2.70255,
      "symbol": "$"
    }
  },
  "AL": {
    "conversionFactor": 0.42,
    "country": {
      "code": "AL",
      "name": "Albania"
    },
    "currency": {
      "code": "all",
      "exchangeRate": 95.052838,
      "symbol": "L"
    }
  },
  "AM": {
    "conversionFactor": 0.43,
    "country": {
      "code": "AM",
      "name": "Armenia"
    },
    "currency": {
      "code": "amd",
      "exchangeRate": 392.897579,
      "symbol": "֏"
    }
  },
  "AO": {
    "conversionFactor": 0.3,
    "country": {
      "code": "AO",
      "name": "Angola"
    },
    "currency": {
      "code": "aoa",
      "exchangeRate": 913.0,
      "symbol": "Kz"
    }
  },
  "AR": {
    "conversionFactor": 0.23,
    "country": {
      "code": "AR",
      "name": "Argentina"
    },
    "currency": {
      "code": "ars",
      "exchangeRate": 998.12,
      "symbol": "$"
    }
  },
  "AT": {
    "conversionFactor": 0.9,
    "country": {
      "code": "AT",
      "name": "Austria"
    },
    "currency": {
      "code": "eur",
      "exchangeRate": 0.95,
      "symbol": "€"
    }
  },
  "AU": {
    "conversionFactor": 1,
    "country": {
      "code": "AU",
      "name": "Australia"
    },
    "currency": {
      "code": "aud",
      "exchangeRate": 1.55,
      "symbol": "$"
    }
  },
  "AW": {
    "conversionFactor": 0.67,
    "country": {
      "code": "AW",
      "name": "Aruba"
    },
    "currency": {
      "code": "awg",
      "exchangeRate": 1.8,
      "symbol": "ƒ"
    }
  },
  "AZ": {
    "conversionFactor": 0.37,
    "country": {
      "code": "AZ",
      "name": "Azerbaijan"
    },
    "currency": {
      "code": "azn",
      "exchangeRate": 1.7,
      "symbol": "₼"
    }
  },
  "BA": {
    "conversionFactor": 0.4,
    "country": {
      "code": "BA",
      "name": "Bosnia and Herzegovina"
    },
    "currency": {
      "code": "bam",
      "exchangeRate": 1.796413,
      "symbol": "KM"
    }
  },
  "BB": {
    "conversionFactor": 1.12,
    "country": {
      "code": "BB",
      "name": "Barbados"
    },
    "currency": {
      "code": "bbd",
      "exchangeRate": 2,
      "symbol": "$"
    }
  },
  "BD": {
    "conversionFactor": 0.29,
    "country": {
      "code": "BD",
      "name": "Bangladesh"
    },
    "currency": {
      "code": "bdt",
      "exchangeRate": 118.81,
      "symbol": "৳"
    }
  },
  "BE": {
    "conversionFactor": 0.9,
    "country": {
      "code": "BE",
      "name": "Belgium"
    },
    "currency": {
      "code": "eur",
      "exchangeRate": 0.95,
      "symbol": "€"
    }
  },
  "BF": {
    "conversionFactor": 0.33,
    "country": {
      "code": "BF",
      "name": "Burkina Faso"
    },
    "currency": {
      "code": "xof",
      "exchangeRate": 616.891014,
      "symbol": "Fr"
    }
  },
  "BG": {
    "conversionFactor": 0.47,
    "country": {
      "code": "BG",
      "name": "Bulgaria"
    },
    "currency": {
      "code": "bgn",
      "exchangeRate": 1.88,
      "symbol": "лв"
    }
  },
  "BH": {
    "conversionFactor": 0.45,
    "country": {
      "code": "BH",
      "name": "Bahrain"
    },
    "currency": {
      "code": "bhd",
      "exchangeRate": 0.376984,
      "symbol": ".د.ب"
    }
  },
  "BI": {
    "conversionFactor": 0.36,
    "country": {
      "code": "BI",
      "name": "Burundi"
    },
    "currency": {
      "code": "bif",
      "exchangeRate": 2868.440313,
      "symbol": "Fr"
    }
  },
  "BJ": {
    "conversionFactor": 0.34,
    "country": {
      "code": "BJ",
      "name": "Benin"
    },
    "currency": {
      "code": "xof",
      "exchangeRate": 626.06,
      "symbol": "Fr"
    }
  },
  "BN": {
    "conversionFactor": 0.45,
    "country": {
      "code": "BN",
      "name": "Brunei Darussalam"
    },
    "currency": {
      "code": "bnd",
      "exchangeRate": 1.361392,
      "symbol": "$"
    }
  },
  "BO": {
    "conversionFactor": 0.37,
    "country": {
      "code": "BO",
      "name": "Bolivia"
    },
    "currency": {
      "code": "bob",
      "exchangeRate": 6.940784,
      "symbol": "Bs."
    }
  },
  "BR": {
    "conversionFactor": 0.52,
    "country": {
      "code": "BR",
      "name": "Brazil"
    },
    "currency": {
      "code": "brl",
      "exchangeRate": 5.82,
      "symbol": "R$"
    }
  },
  "BS": {
    "conversionFactor": 0.8,
    "country": {
      "code": "BS",
      "name": "Bahamas"
    },
    "currency": {
      "code": "bsd",
      "exchangeRate": 1,
      "symbol": "$"
    }
  },
  "BT": {
    "conversionFactor": 0.25,
    "country": {
      "code": "BT",
      "name": "Bhutan"
    },
    "currency": {
      "code": "btn",
      "exchangeRate": 83.43308,
      "symbol": "Nu."
    }
  },
  "BW": {
    "conversionFactor": 0.36,
    "country": {
      "code": "BW",
      "name": "Botswana"
    },
    "currency": {
      "code": "bwp",
      "exchangeRate": 13.880363,
      "symbol": "P"
    }
  },
  "BY": {
    "conversionFactor": 0.31,
    "country": {
      "code": "BY",
      "name": "Belarus"
    },
    "currency": {
      "code": "byn",
      "exchangeRate": 3.274961,
      "symbol": "Br"
    }
  },
  "BZ": {
    "conversionFactor": 0.64,
    "country": {
      "code": "BZ",
      "name": "Belize"
    },
    "currency": {
      "code": "bzd",
      "exchangeRate": 2.017413,
      "symbol": "$"
    }
  },
  "CA": {
    "conversionFactor": 0.9,
    "country": {
      "code": "CA",
      "name": "Canada"
    },
    "currency": {
      "code": "cad",
      "exchangeRate": 1.39,
      "symbol": "$"
    }
  },
  "CD": {
    "conversionFactor": 0.36,
    "country": {
      "code": "CD",
      "name": "Congo, The Democratic Republic of the"
    },
    "currency": {
      "code": "cdf",
      "exchangeRate": 2787.382669,
      "symbol": "FC"
    }
  },
  "CF": {
    "conversionFactor": 0.47,
    "country": {
      "code": "CF",
      "name": "Central African Republic"
    },
    "currency": {
      "code": "xaf",
      "exchangeRate": 616.891014,
      "symbol": "Fr"
    }
  },
  "CG": {
    "conversionFactor": 0.3,
    "country": {
      "code": "CG",
      "name": "Congo"
    },
    "currency": {
      "code": "xaf",
      "exchangeRate": 626.06,
      "symbol": "Fr"
    }
  },
  "CH": {
    "conversionFactor": 1.1,
    "country": {
      "code": "CH",
      "name": "Switzerland"
    },
    "currency": {
      "code": "chf",
      "exchangeRate": 0.81,
      "symbol": "Fr."
    }
  },
  "CI": {
    "conversionFactor": 0.4,
    "country": {
      "code": "CI",
      "name": "Cote D'Ivoire"
    },
    "currency": {
      "code": "xof",
      "exchangeRate": 626.06,
      "symbol": "Fr"
    }
  },
  "CL": {
    "conversionFactor": 0.6,
    "country": {
      "code": "CL",
      "name": "Chile"
    },
    "currency": {
      "code": "clp",
      "exchangeRate": 972.51,
      "symbol": "$"
    }
  },
  "CM": {
    "conversionFactor": 0.4,
    "country": {
      "code": "CM",
      "name": "Cameroon"
    },
    "currency": {
      "code": "xaf",
      "exchangeRate": 626.06,
      "symbol": "Fr"
    }
  },
  "CN": {
    "conversionFactor": 0.6,
    "country": {
      "code": "CN",
      "name": "China"
    },
    "currency": {
      "code": "cny",
      "exchangeRate": 7.2438,
      "symbol": "¥"
    }
  },
  "CO": {
    "conversionFactor": 0.41,
    "country": {
      "code": "CO",
      "name": "Colombia"
    },
    "currency": {
      "code": "cop",
      "exchangeRate": 3927.33,
      "symbol": "$"
    }
  },
  "CR": {
    "conversionFactor": 0.68,
    "country": {
      "code": "CR",
      "name": "Costa Rica"
    },
    "currency": {
      "code": "crc",
      "exchangeRate": 501.882235,
      "symbol": "₡"
    }
  },
  "CV": {
    "conversionFactor": 0.44,
    "country": {
      "code": "CV",
      "name": "Cape Verde"
    },
    "currency": {
      "code": "cve",
      "exchangeRate": 103.497294,
      "symbol": "Esc"
    }
  },
  "CW": {
    "conversionFactor": 0.8,
    "country": {
      "code": "CW",
      "name": "Curaçao"
    },
    "currency": {
      "code": "ang",
      "exchangeRate": 1.8,
      "symbol": "ƒ"
    }
  },
  "CY": {
    "conversionFactor": 0.7,
    "country": {
      "code": "CY",
      "name": "Cyprus"
    },
    "currency": {
      "code": "eur",
      "exchangeRate": 0.95,
      "symbol": "€"
    }
  },
  "CZ": {
    "conversionFactor": 0.6,
    "country": {
      "code": "CZ",
      "name": "Czech Republic"
    },
    "currency": {
      "code": "czk",
      "exchangeRate": 23.7471,
      "symbol": "Kč"
    }
  },
  "DE": {
    "conversionFactor": 0.9,
    "country": {
      "code": "DE",
      "name": "Germany"
    },
    "currency": {
      "code": "eur",
      "exchangeRate": 0.940223,
      "symbol": "€"
    }
  },
  "DJ": {
    "conversionFactor": 0.6,
    "country": {
      "code": "DJ",
      "name": "Djibouti"
    },
    "currency": {
      "code": "djf",
      "exchangeRate": 177.961336,
      "symbol": "Fr"
    }
  },
  "DK": {
    "conversionFactor": 1,
    "country": {
      "code": "DK",
      "name": "Denmark"
    },
    "currency": {
      "code": "dkk",
      "exchangeRate": 7.008672,
      "symbol": "kr"
    }
  },
  "DM": {
    "conversionFactor": 0.7,
    "country": {
      "code": "DM",
      "name": "Dominica"
    },
    "currency": {
      "code": "xcd",
      "exchangeRate": 2.70255,
      "symbol": "$"
    }
  },
  "DO": {
    "conversionFactor": 0.42,
    "country": {
      "code": "DO",
      "name": "Dominican Republic"
    },
    "currency": {
      "code": "dop",
      "exchangeRate": 58.973706,
      "symbol": "$"
    }
  },
  "DZ": {
    "conversionFactor": 0.36,
    "country": {
      "code": "DZ",
      "name": "Algeria"
    },
    "currency": {
      "code": "dzd",
      "exchangeRate": 134.811379,
      "symbol": "د.ج"
    }
  },
  "EC": {
    "conversionFactor": 0.5,
    "country": {
      "code": "EC",
      "name": "Ecuador"
    },
    "currency": {
      "code": "usd",
      "exchangeRate": 1,
      "symbol": "$"
    }
  },
  "EE": {
    "conversionFactor": 0.65,
    "country": {
      "code": "EE",
      "name": "Estonia"
    },
    "currency": {
      "code": "eur",
      "exchangeRate": 0.95,
      "symbol": "€"
    }
  },
  "EG": {
    "conversionFactor": 0.13,
    "country": {
      "code": "EG",
      "name": "Egypt"
    },
    "currency": {
      "code": "egp",
      "exchangeRate": 49.37,
      "symbol": "£"
    }
  },
  "ER": {
    "conversionFactor": 0.34,
    "country": {
      "code": "ER",
      "name": "Eritrea"
    },
    "currency": {
      "code": "ern",
      "exchangeRate": 15,
      "symbol": "Nfk"
    }
  },
  "ES": {
    "conversionFactor": 0.7,
    "country": {
      "code": "ES",
      "name": "Spain"
    },
    "currency": {
      "code": "eur",
      "exchangeRate": 0.95,
      "symbol": "€"
    }
  },
  "ET": {
    "conversionFactor": 0.48,
    "country": {
      "code": "ET",
      "name": "Ethiopia"
    },
    "currency": {
      "code": "etb",
      "exchangeRate": 141.17,
      "symbol": "Br"
    }
  },
  "FI": {
    "conversionFactor": 1,
    "country": {
      "code": "FI",
      "name": "Finland"
    },
    "currency": {
      "code": "eur",
      "exchangeRate": 0.95,
      "symbol": "€"
    }
  },
  "FJ": {
    "conversionFactor": 0.37,
    "country": {
      "code": "FJ",
      "name": "Fiji"
    },
    "currency": {
      "code": "fjd",
      "exchangeRate": 2.2733,
      "symbol": "$"
    }
  },
  "FM": {
    "conversionFactor": 1,
    "country": {
      "code": "FM",
      "name": "Micronesia, Federated States of"
    },
    "currency": {
      "code": "usd",
      "exchangeRate": 1,
      "symbol": "$"
    }
  },
  "FR": {
    "conversionFactor": 0.9,
    "country": {
      "code": "FR",
      "name": "France"
    },
    "currency": {
      "code": "eur",
      "exchangeRate": 0.95,
      "symbol": "€"
    }
  },
  "GA": {
    "conversionFactor": 0.4,
    "country": {
      "code": "GA",
      "name": "Gabon"
    },
    "currency": {
      "code": "xaf",
      "exchangeRate": 626.06,
      "symbol": "Fr"
    }
  },
  "GB": {
    "conversionFactor": 0.9,
    "country": {
      "code": "GB",
      "name": "United Kingdom"
    },
    "currency": {
      "code": "gbp",
      "exchangeRate": 0.79,
      "symbol": "£"
    }
  },
  "GD": {
    "conversionFactor": 0.7,
    "country": {
      "code": "GD",
      "name": "Grenada"
    },
    "currency": {
      "code": "xcd",
      "exchangeRate": 2.70255,
      "symbol": "$"
    }
  },
  "GE": {
    "conversionFactor": 0.38,
    "country": {
      "code": "GE",
      "name": "Georgia"
    },
    "currency": {
      "code": "gel",
      "exchangeRate": 2.74,
      "symbol": "₾"
    }
  },
  "GH": {
    "conversionFactor": 0.33,
    "country": {
      "code": "GH",
      "name": "Ghana"
    },
    "currency": {
      "code": "ghs",
      "exchangeRate": 13.461511,
      "symbol": "₵"
    }
  },
  "GM": {
    "conversionFactor": 0.29,
    "country": {
      "code": "GM",
      "name": "Gambia"
    },
    "currency": {
      "code": "gmd",
      "exchangeRate": 67.9,
      "symbol": "D"
    }
  },
  "GN": {
    "conversionFactor": 0.51,
    "country": {
      "code": "GN",
      "name": "Guinea"
    },
    "currency": {
      "code": "gnf",
      "exchangeRate": 8603.253044,
      "symbol": "Fr"
    }
  },
  "GQ": {
    "conversionFactor": 0.4,
    "country": {
      "code": "GQ",
      "name": "Equatorial Guinea"
    },
    "currency": {
      "code": "xaf",
      "exchangeRate": 626.06,
      "symbol": "Fr"
    }
  },
  "GR": {
    "conversionFactor": 0.65,
    "country": {
      "code": "GR",
      "name": "Greece"
    },
    "currency": {
      "code": "eur",
      "exchangeRate": 0.95,
      "symbol": "€"
    }
  },
  "GT": {
    "conversionFactor": 0.55,
    "country": {
      "code": "GT",
      "name": "Guatemala"
    },
    "currency": {
      "code": "gtq",
      "exchangeRate": 7.772741,
      "symbol": "Q"
    }
  },
  "GW": {
    "conversionFactor": 0.4,
    "country": {
      "code": "GW",
      "name": "Guinea-Bissau"
    },
    "currency": {
      "code": "xof",
      "exchangeRate": 626.06,
      "symbol": "Fr"
    }
  },
  "GY": {
    "conversionFactor": 0.31,
    "country": {
      "code": "GY",
      "name": "Guyana"
    },
    "currency": {
      "code": "gyd",
      "exchangeRate": 209.398128,
      "symbol": "$"
    }
  },
  "HK": {
    "conversionFactor": 0.8,
    "country": {
      "code": "HK",
      "name": "Hong Kong"
    },
    "currency": {
      "code": "hkd",
      "exchangeRate": 7.78,
      "symbol": "$"
    }
  },
  "HN": {
    "conversionFactor": 0.47,
    "country": {
      "code": "HN",
      "name": "Honduras"
    },
    "currency": {
      "code": "hnl",
      "exchangeRate": 24.708099,
      "symbol": "L"
    }
  },
  "HR": {
    "conversionFactor": 0.5,
    "country": {
      "code": "HR",
      "name": "Croatia"
    },
    "currency": {
      "code": "eur",
      "exchangeRate": 0.95,
      "symbol": "€"
    }
  },
  "HT": {
    "conversionFactor": 0.65,
    "country": {
      "code": "HT",
      "name": "Haiti"
    },
    "currency": {
      "code": "htg",
      "exchangeRate": 132.716872,
      "symbol": "G"
    }
  },
  "HU": {
    "conversionFactor": 0.44,
    "country": {
      "code": "HU",
      "name": "Hungary"
    },
    "currency": {
      "code": "huf",
      "exchangeRate": 392.59,
      "symbol": "Ft"
    }
  },
  "ID": {
    "conversionFactor": 0.3,
    "country": {
      "code": "ID",
      "name": "Indonesia"
    },
    "currency": {
      "code": "idr",
      "exchangeRate": 15862.01,
      "symbol": "Rp"
    }
  },
  "IE": {
    "conversionFactor": 0.9,
    "country": {
      "code": "IE",
      "name": "Ireland"
    },
    "currency": {
      "code": "eur",
      "exchangeRate": 0.95,
      "symbol": "€"
    }
  },
  "IL": {
    "conversionFactor": 1.1,
    "country": {
      "code": "IL",
      "name": "Israel"
    },
    "currency": {
      "code": "ils",
      "exchangeRate": 3.38,
      "symbol": "₪"
    }
  },
  "IN": {
    "conversionFactor": 0.29,
    "country": {
      "code": "IN",
      "name": "India"
    },
    "currency": {
      "code": "inr",
      "exchangeRate": 84.31,
      "symbol": "₹"
    }
  },
  "IQ": {
    "conversionFactor": 0.47,
    "country": {
      "code": "IQ",
      "name": "Iraq"
    },
    "currency": {
      "code": "iqd",
      "exchangeRate": 1312.132895,
      "symbol": "ع.د"
    }
  },
  "IR": {
    "conversionFactor": 0.75,
    "country": {
      "code": "IR",
      "name": "Iran, Islamic Republic Of"
    },
    "currency": {
      "code": "irr",
      "exchangeRate": 42272.5,
      "symbol": "﷼"
    }
  },
  "IS": {
    "conversionFactor": 1.1,
    "country": {
      "code": "IS",
      "name": "Iceland"
    },
    "currency": {
      "code": "isk",
      "exchangeRate": 141.2,
      "symbol": "kr"
    }
  },
  "IT": {
    "conversionFactor": 0.8,
    "country": {
      "code": "IT",
      "name": "Italy"
    },
    "currency": {
      "code": "eur",
      "exchangeRate": 0.95,
      "symbol": "€"
    }
  },
  "JM": {
    "conversionFactor": 0.49,
    "country": {
      "code": "JM",
      "name": "Jamaica"
    },
    "currency": {
      "code": "jmd",
      "exchangeRate": 155.755147,
      "symbol": "$"
    }
  },
  "JO": {
    "conversionFactor": 0.4,
    "country": {
      "code": "JO",
      "name": "Jordan"
    },
    "currency": {
      "code": "jod",
      "exchangeRate": 0.7087,
      "symbol": "د.ا"
    }
  },
  "JP": {
    "conversionFactor": 0.7,
    "country": {
      "code": "JP",
      "name": "Japan"
    },
    "currency": {
      "code": "jpy",
      "exchangeRate": 154.7325,
      "symbol": "¥"
    }
  },
  "KE": {
    "conversionFactor": 0.35,
    "country": {
      "code": "KE",
      "name": "Kenya"
    },
    "currency": {
      "code": "kes",
      "exchangeRate": 134,
      "symbol": "Sh"
    }
  },
  "KG": {
    "conversionFactor": 0.29,
    "country": {
      "code": "KG",
      "name": "Kyrgyzstan"
    },
    "currency": {
      "code": "kgs",
      "exchangeRate": 88.906,
      "symbol": "с"
    }
  },
  "KH": {
    "conversionFactor": 0.33,
    "country": {
      "code": "KH",
      "name": "Cambodia"
    },
    "currency": {
      "code": "khr",
      "exchangeRate": 4061.437286,
      "symbol": "៛"
    }
  },
  "KI": {
    "conversionFactor": 0.7,
    "country": {
      "code": "KI",
      "name": "Kiribati"
    },
    "currency": {
      "code": "aud",
      "exchangeRate": 1.53,
      "symbol": "$"
    }
  },
  "KM": {
    "conversionFactor": 0.39,
    "country": {
      "code": "KM",
      "name": "Comoros"
    },
    "currency": {
      "code": "kmf",
      "exchangeRate": 472.5,
      "symbol": "Fr"
    }
  },
  "KN": {
    "conversionFactor": 0.6,
    "country": {
      "code": "KN",
      "name": "Saint Kitts and Nevis"
    },
    "currency": {
      "code": "xcd",
      "exchangeRate": 2.70255,
      "symbol": "$"
    }
  },
  "KR": {
    "conversionFactor": 0.6,
    "country": {
      "code": "KR",
      "name": "Korea, Republic of"
    },
    "currency": {
      "code": "krw",
      "exchangeRate": 1399.28,
      "symbol": "₩"
    }
  },
  "KW": {
    "conversionFactor": 0.62,
    "country": {
      "code": "KW",
      "name": "Kuwait"
    },
    "currency": {
      "code": "kwd",
      "exchangeRate": 0.308332,
      "symbol": "د.ك"
    }
  },
  "KZ": {
    "conversionFactor": 0.43,
    "country": {
      "code": "KZ",
      "name": "Kazakhstan"
    },
    "currency": {
      "code": "kzt",
      "exchangeRate": 496.4,
      "symbol": "₸"
    }
  },
  "LA": {
    "conversionFactor": 0.2,
    "country": {
      "code": "LA",
      "name": "Lao People's Democratic Republic"
    },
    "currency": {
      "code": "lak",
      "exchangeRate": 21835.83,
      "symbol": "₭"
    }
  },
  "LB": {
    "conversionFactor": 0.1,
    "country": {
      "code": "LB",
      "name": "Lebanon"
    },
    "currency": {
      "code": "lbp",
      "exchangeRate": 89777,
      "symbol": "ل.ل"
    }
  },
  "LC": {
    "conversionFactor": 0.75,
    "country": {
      "code": "LC",
      "name": "Saint Lucia"
    },
    "currency": {
      "code": "xcd",
      "exchangeRate": 2.70255,
      "symbol": "$"
    }
  },
  "LK": {
    "conversionFactor": 0.33,
    "country": {
      "code": "LK",
      "name": "Sri Lanka"
    },
    "currency": {
      "code": "lkr",
      "exchangeRate": 289.37,
      "symbol": "Rs  රු"
    }
  },
  "LR": {
    "conversionFactor": 0,
    "country": {
      "code": "LR",
      "name": "Liberia"
    },
    "currency": {
      "code": "lrd",
      "exchangeRate": 193.200023,
      "symbol": "$"
    }
  },
  "LS": {
    "conversionFactor": 0.35,
    "country": {
      "code": "LS",
      "name": "Lesotho"
    },
    "currency": {
      "code": "lsl",
      "exchangeRate": 19.107171,
      "symbol": "L"
    }
  },
  "LT": {
    "conversionFactor": 0.5,
    "country": {
      "code": "LT",
      "name": "Lithuania"
    },
    "currency": {
      "code": "eur",
      "exchangeRate": 0.95,
      "symbol": "€"
    }
  },
  "LU": {
    "conversionFactor": 1,
    "country": {
      "code": "LU",
      "name": "Luxembourg"
    },
    "currency": {
      "code": "eur",
      "exchangeRate": 0.95,
      "symbol": "€"
    }
  },
  "LV": {
    "conversionFactor": 0.6,
    "country": {
      "code": "LV",
      "name": "Latvia"
    },
    "currency": {
      "code": "eur",
      "exchangeRate": 0.95,
      "symbol": "€"
    }
  },
  "LY": {
    "conversionFactor": 0.25,
    "country": {
      "code": "LY",
      "name": "Libyan Arab Jamahiriya"
    },
    "currency": {
      "code": "lyd",
      "exchangeRate": 4.879974,
      "symbol": "ل.د"
    }
  },
  "MA": {
    "conversionFactor": 0.38,
    "country": {
      "code": "MA",
      "name": "Morocco"
    },
    "currency": {
      "code": "mad",
      "exchangeRate": 10.12418,
      "symbol": "د.م."
    }
  },
  "MD": {
    "conversionFactor": 0.42,
    "country": {
      "code": "MD",
      "name": "Moldova, Republic of"
    },
    "currency": {
      "code": "mdl",
      "exchangeRate": 17.865046,
      "symbol": "L"
    }
  },
  "ME": {
    "conversionFactor": 0.4,
    "country": {
      "code": "ME",
      "name": "Montenegro"
    },
    "currency": {
      "code": "eur",
      "exchangeRate": 0.95,
      "symbol": "€"
    }
  },
  "MG": {
    "conversionFactor": 0.3,
    "country": {
      "code": "MG",
      "name": "Madagascar"
    },
    "currency": {
      "code": "mga",
      "exchangeRate": 4429.865258,
      "symbol": "Ar"
    }
  },
  "MH": {
    "conversionFactor": 1.004,
    "country": {
      "code": "MH",
      "name": "Marshall Islands"
    },
    "currency": {
      "code": "usd",
      "exchangeRate": 1,
      "symbol": "$"
    }
  },
  "MK": {
    "conversionFactor": 0.36,
    "country": {
      "code": "MK",
      "name": "Macedonia, The Former Yugoslav Republic of"
    },
    "currency": {
      "code": "mkd",
      "exchangeRate": 57.852836,
      "symbol": "den"
    }
  },
  "ML": {
    "conversionFactor": 0.36,
    "country": {
      "code": "ML",
      "name": "Mali"
    },
    "currency": {
      "code": "xof",
      "exchangeRate": 626.06,
      "symbol": "Fr"
    }
  },
  "MM": {
    "conversionFactor": 0.25,
    "country": {
      "code": "MM",
      "name": "Myanmar"
    },
    "currency": {
      "code": "mmk",
      "exchangeRate": 2098.655704,
      "symbol": "Ks"
    }
  },
  "MN": {
    "conversionFactor": 0.36,
    "country": {
      "code": "MN",
      "name": "Mongolia"
    },
    "currency": {
      "code": "mnt",
      "exchangeRate": 3450,
      "symbol": "₮"
    }
  },
  "MO": {
    "conversionFactor": 0.6,
    "country": {
      "code": "MO",
      "name": "Macao"
    },
    "currency": {
      "code": "mop",
      "exchangeRate": 8.077923,
      "symbol": "P"
    }
  },
  "MR": {
    "conversionFactor": 0.33,
    "country": {
      "code": "MR",
      "name": "Mauritania"
    },
    "currency": {
      "code": "mru",
      "exchangeRate": 39.564854,
      "symbol": "UM"
    }
  },
  "MT": {
    "conversionFactor": 0.65,
    "country": {
      "code": "MT",
      "name": "Malta"
    },
    "currency": {
      "code": "eur",
      "exchangeRate": 0.95,
      "symbol": "€"
    }
  },
  "MU": {
    "conversionFactor": 0.39,
    "country": {
      "code": "MU",
      "name": "Mauritius"
    },
    "currency": {
      "code": "mur",
      "exchangeRate": 46.529109,
      "symbol": "₨"
    }
  },
  "MV": {
    "conversionFactor": 0.49,
    "country": {
      "code": "MV",
      "name": "Maldives"
    },
    "currency": {
      "code": "mvr",
      "exchangeRate": 15.45,
      "symbol": ".ރ"
    }
  },
  "MW": {
    "conversionFactor": 0.25,
    "country": {
      "code": "MW",
      "name": "Malawi"
    },
    "currency": {
      "code": "mwk",
      "exchangeRate": 1734.914212,
      "symbol": "MK"
    }
  },
  "MX": {
    "conversionFactor": 0.59,
    "country": {
      "code": "MX",
      "name": "Mexico"
    },
    "currency": {
      "code": "mxn",
      "exchangeRate": 20.37,
      "symbol": "$"
    }
  },
  "MY": {
    "conversionFactor": 0.33,
    "country": {
      "code": "MY",
      "name": "Malaysia"
    },
    "currency": {
      "code": "myr",
      "exchangeRate": 4.44,
      "symbol": "RM"
    }
  },
  "MZ": {
    "conversionFactor": 0.4,
    "country": {
      "code": "MZ",
      "name": "Mozambique"
    },
    "currency": {
      "code": "mzn",
      "exchangeRate": 64.050002,
      "symbol": "MT"
    }
  },
  "NA": {
    "conversionFactor": 0.39,
    "country": {
      "code": "NA",
      "name": "Namibia"
    },
    "currency": {
      "code": "nad",
      "exchangeRate": 17.94,
      "symbol": "$"
    }
  },
  "NE": {
    "conversionFactor": 0.35,
    "country": {
      "code": "NE",
      "name": "Niger"
    },
    "currency": {
      "code": "xof",
      "exchangeRate": 626.06,
      "symbol": "Fr"
    }
  },
  "NG": {
    "conversionFactor": 0.15,
    "country": {
      "code": "NG",
      "name": "Nigeria"
    },
    "currency": {
      "code": "ngn",
      "exchangeRate": 1688.46,
      "symbol": "₦"
    }
  },
  "NI": {
    "conversionFactor": 0.35,
    "country": {
      "code": "NI",
      "name": "Nicaragua"
    },
    "currency": {
      "code": "nio",
      "exchangeRate": 36.837084,
      "symbol": "C$"
    }
  },
  "NL": {
    "conversionFactor": 0.9,
    "country": {
      "code": "NL",
      "name": "Netherlands"
    },
    "currency": {
      "code": "eur",
      "exchangeRate": 0.95,
      "symbol": "€"
    }
  },
  "NO": {
    "conversionFactor": 1.1,
    "country": {
      "code": "NO",
      "name": "Norway"
    },
    "currency": {
      "code": "nok",
      "exchangeRate": 11.03222,
      "symbol": "kr"
    }
  },
  "NP": {
    "conversionFactor": 0.27,
    "country": {
      "code": "NP",
      "name": "Nepal"
    },
    "currency": {
      "code": "npr",
      "exchangeRate": 133.493064,
      "symbol": "₨"
    }
  },
  "NR": {
    "conversionFactor": 0.65,
    "country": {
      "code": "NR",
      "name": "Nauru"
    },
    "currency": {
      "code": "aud",
      "exchangeRate": 1.53,
      "symbol": "$"
    }
  },
  "NZ": {
    "conversionFactor": 1,
    "country": {
      "code": "NZ",
      "name": "New Zealand"
    },
    "currency": {
      "code": "nzd",
      "exchangeRate": 1.71,
      "symbol": "$"
    }
  },
  "OM": {
    "conversionFactor": 0.52,
    "country": {
      "code": "OM",
      "name": "Oman"
    },
    "currency": {
      "code": "omr",
      "exchangeRate": 0.384967,
      "symbol": "ر.ع."
    }
  },
  "PA": {
    "conversionFactor": 0.43,
    "country": {
      "code": "PA",
      "name": "Panama"
    },
    "currency": {
      "code": "pab",
      "exchangeRate": 1,
      "symbol": "B/."
    }
  },
  "PE": {
    "conversionFactor": 0.5,
    "country": {
      "code": "PE",
      "name": "Peru"
    },
    "currency": {
      "code": "pen",
      "exchangeRate": 3.77,
      "symbol": "S/ "
    }
  },
  "PG": {
    "conversionFactor": 0.7,
    "country": {
      "code": "PG",
      "name": "Papua New Guinea"
    },
    "currency": {
      "code": "pgk",
      "exchangeRate": 4.0,
      "symbol": "K"
    }
  },
  "PH": {
    "conversionFactor": 0.35,
    "country": {
      "code": "PH",
      "name": "Philippines"
    },
    "currency": {
      "code": "php",
      "exchangeRate": 58.99,
      "symbol": "₱"
    }
  },
  "PK": {
    "conversionFactor": 0.25,
    "country": {
      "code": "PK",
      "name": "Pakistan"
    },
    "currency": {
      "code": "pkr",
      "exchangeRate": 276.08,
      "symbol": "₨"
    }
  },
  "PL": {
    "conversionFactor": 0.5,
    "country": {
      "code": "PL",
      "name": "Poland"
    },
    "currency": {
      "code": "pln",
      "exchangeRate": 4.14,
      "symbol": "zł"
    }
  },
  "PR": {
    "conversionFactor": 0.8,
    "country": {
      "code": "PR",
      "name": "Puerto Rico"
    },
    "currency": {
      "code": "usd",
      "exchangeRate": 1,
      "symbol": "$"
    }
  },
  "PS": {
    "conversionFactor": 0.4,
    "country": {
      "code": "PS",
      "name": "Palestine"
    },
    "currency": {
      "code": "ils",
      "exchangeRate": 3.7,
      "symbol": "₪"
    }
  },
  "PT": {
    "conversionFactor": 0.7,
    "country": {
      "code": "PT",
      "name": "Portugal"
    },
    "currency": {
      "code": "eur",
      "exchangeRate": 0.95,
      "symbol": "€"
    }
  },
  "PW": {
    "conversionFactor": 1.1,
    "country": {
      "code": "PW",
      "name": "Palau"
    },
    "currency": {
      "code": "usd",
      "exchangeRate": 1,
      "symbol": "$"
    }
  },
  "PY": {
    "conversionFactor": 0.35,
    "country": {
      "code": "PY",
      "name": "Paraguay"
    },
    "currency": {
      "code": "pyg",
      "exchangeRate": 7761,
      "symbol": "₲"
    }
  },
  "QA": {
    "conversionFactor": 0.7,
    "country": {
      "code": "QA",
      "name": "Qatar"
    },
    "currency": {
      "code": "qar",
      "exchangeRate": 3.65,
      "symbol": "ر.ق"
    }
  },
  "RO": {
    "conversionFactor": 0.45,
    "country": {
      "code": "RO",
      "name": "Romania"
    },
    "currency": {
      "code": "ron",
      "exchangeRate": 4.75,
      "symbol": "lei"
    }
  },
  "RS": {
    "conversionFactor": 0.45,
    "country": {
      "code": "RS",
      "name": "Serbia"
    },
    "currency": {
      "code": "rsd",
      "exchangeRate": 111.65,
      "symbol": "дин."
    }
  },
  "RU": {
    "conversionFactor": 0.35,
    "country": {
      "code": "RU",
      "name": "Russian Federation"
    },
    "currency": {
      "code": "rub",
      "exchangeRate": 103.72,
      "symbol": "₽"
    }
  },
  "RW": {
    "conversionFactor": 0.3,
    "country": {
      "code": "RW",
      "name": "RWANDA"
    },
    "currency": {
      "code": "rwf",
      "exchangeRate": 1357.19,
      "symbol": "Fr"
    }
  },
  "SA": {
    "conversionFactor": 0.45,
    "country": {
      "code": "SA",
      "name": "Saudi Arabia"
    },
    "currency": {
      "code": "sar",
      "exchangeRate": 3.750811,
      "symbol": "ر.س"
    }
  },
  "SB": {
    "conversionFactor": 0.95,
    "country": {
      "code": "SB",
      "name": "Solomon Islands"
    },
    "currency": {
      "code": "sbd",
      "exchangeRate": 8.38,
      "symbol": "$"
    }
  },
  "SC": {
    "conversionFactor": 0.5,
    "country": {
      "code": "SC",
      "name": "Seychelles"
    },
    "currency": {
      "code": "scr",
      "exchangeRate": 13.62,
      "symbol": "₨"
    }
  },
  "SD": {
    "conversionFactor": 0.075,
    "country": {
      "code": "SD",
      "name": "Sudan"
    },
    "currency": {
      "code": "sdg",
      "exchangeRate": 601.5,
      "symbol": "LS"
    }
  },
  "SE": {
    "conversionFactor": 0.9,
    "country": {
      "code": "SE",
      "name": "Sweden"
    },
    "currency": {
      "code": "sek",
      "exchangeRate": 10.98,
      "symbol": "kr"
    }
  },
  "SG": {
    "conversionFactor": 0.7,
    "country": {
      "code": "SG",
      "name": "Singapore"
    },
    "currency": {
      "code": "sgd",
      "exchangeRate": 1.25,
      "symbol": "$"
    }
  },
  "SI": {
    "conversionFactor": 0.7,
    "country": {
      "code": "SI",
      "name": "Slovenia"
    },
    "currency": {
      "code": "eur",
      "exchangeRate": 0.95,
      "symbol": "€"
    }
  },
  "SK": {
    "conversionFactor": 0.6,
    "country": {
      "code": "SK",
      "name": "Slovakia"
    },
    "currency": {
      "code": "eur",
      "exchangeRate": 0.95,
      "symbol": "€"
    }
  },
  "SL": {
    "conversionFactor": 0.2,
    "country": {
      "code": "SL",
      "name": "Sierra Leone"
    },
    "currency": {
      "code": "sll",
      "exchangeRate": 22726,
      "symbol": "Le"
    }
  },
  "SM": {
    "conversionFactor": 0.75,
    "country": {
      "code": "SM",
      "name": "San Marino"
    },
    "currency": {
      "code": "eur",
      "exchangeRate": 0.95,
      "symbol": "€"
    }
  },
  "SN": {
    "conversionFactor": 0.4,
    "country": {
      "code": "SN",
      "name": "Senegal"
    },
    "currency": {
      "code": "xof",
      "exchangeRate": 626.06,
      "symbol": "Fr"
    }
  },
  "SO": {
    "conversionFactor": 0,
    "country": {
      "code": "SO",
      "name": "Somalia"
    },
    "currency": {
      "code": "sos",
      "exchangeRate": 565.6,
      "symbol": "Sh"
    }
  },
  "SR": {
    "conversionFactor": 0.4,
    "country": {
      "code": "SR",
      "name": "Suriname"
    },
    "currency": {
      "code": "srd",
      "exchangeRate": 35.49,
      "symbol": "$"
    }
  },
  "ST": {
    "conversionFactor": 0.6,
    "country": {
      "code": "ST",
      "name": "Sao Tome and Principe"
    },
    "currency": {
      "code": "stn",
      "exchangeRate": 23.023178,
      "symbol": "Db"
    }
  },
  "SV": {
    "conversionFactor": 0.5,
    "country": {
      "code": "SV",
      "name": "El Salvador"
    },
    "currency": {
      "code": "usd",
      "exchangeRate": 1,
      "symbol": "$"
    }
  },
  "SY": {
    "conversionFactor": 0.4,
    "country": {
      "code": "SY",
      "name": "Syria"
    },
    "currency": {
      "code": "syp",
      "exchangeRate": 13001,
      "symbol": "LS"
    }
  },
  "SZ": {
    "conversionFactor": 0.33,
    "country": {
      "code": "SZ",
      "name": "Swaziland"
    },
    "currency": {
      "code": "szl",
      "exchangeRate": 17.93,
      "symbol": "L"
    }
  },
  "TD": {
    "conversionFactor": 0.35,
    "country": {
      "code": "TD",
      "name": "Chad"
    },
    "currency": {
      "code": "xaf",
      "exchangeRate": 626.06,
      "symbol": "Fr"
    }
  },
  "TG": {
    "conversionFactor": 0.4,
    "country": {
      "code": "TG",
      "name": "Togo"
    },
    "currency": {
      "code": "xof",
      "exchangeRate": 626.06,
      "symbol": "Fr"
    }
  },
  "TH": {
    "conversionFactor": 0.3,
    "country": {
      "code": "TH",
      "name": "Thailand"
    },
    "currency": {
      "code": "thb",
      "exchangeRate": 34.53,
      "symbol": "฿"
    }
  },
  "TJ": {
    "conversionFactor": 0.25,
    "country": {
      "code": "TJ",
      "name": "Tajikistan"
    },
    "currency": {
      "code": "tjs",
      "exchangeRate": 10.65,
      "symbol": "ЅМ"
    }
  },
  "TL": {
    "conversionFactor": 0.6,
    "country": {
      "code": "TL",
      "name": "Timor-Leste"
    },
    "currency": {
      "code": "usd",
      "exchangeRate": 1,
      "symbol": "$"
    }
  },
  "TM": {
    "conversionFactor": 0.7,
    "country": {
      "code": "TM",
      "name": "Turkmenistan"
    },
    "currency": {
      "code": "tmt",
      "exchangeRate": 3.51,
      "symbol": "m"
    }
  },
  "TN": {
    "conversionFactor": 0.35,
    "country": {
      "code": "TN",
      "name": "Tunisia"
    },
    "currency": {
      "code": "tnd",
      "exchangeRate": 3.151,
      "symbol": "د.ت"
    }
  },
  "TO": {
    "conversionFactor": 0.8,
    "country": {
      "code": "TO",
      "name": "Tonga"
    },
    "currency": {
      "code": "top",
      "exchangeRate": 2.39395,
      "symbol": "T$"
    }
  },
  "TR": {
    "conversionFactor": 0.25,
    "country": {
      "code": "TR",
      "name": "Turkey"
    },
    "currency": {
      "code": "try",
      "exchangeRate": 40,
      "symbol": "₺"
    }
  },
  "TT": {
    "conversionFactor": 0.65,
    "country": {
      "code": "TT",
      "name": "Trinidad and Tobago"
    },
    "currency": {
      "code": "ttd",
      "exchangeRate": 6.786184,
      "symbol": "$"
    }
  },
  "TV": {
    "conversionFactor": 0.9,
    "country": {
      "code": "TV",
      "name": "Tuvalu"
    },
    "currency": {
      "code": "aud",
      "exchangeRate": 1.53,
      "symbol": "$"
    }
  },
  "TW": {
    "conversionFactor": 0.4,
    "country": {
      "code": "TW",
      "name": "Taiwan, Province of China"
    },
    "currency": {
      "code": "twd",
      "exchangeRate": 32.45,
      "symbol": "$"
    }
  },
  "TZ": {
    "conversionFactor": 0.35,
    "country": {
      "code": "TZ",
      "name": "Tanzania"
    },
    "currency": {
      "code": "tzs",
      "exchangeRate": 2650,
      "symbol": "Sh"
    }
  },
  "UA": {
    "conversionFactor": 0.3,
    "country": {
      "code": "UA",
      "name": "Ukraine"
    },
    "currency": {
      "code": "uah",
      "exchangeRate": 41.13,
      "symbol": "₴"
    }
  },
  "UG": {
    "conversionFactor": 0.4,
    "country": {
      "code": "UG",
      "name": "Uganda"
    },
    "currency": {
      "code": "ugx",
      "exchangeRate": 3694.04,
      "symbol": "Sh"
    }
  },
  "US": {
    "conversionFactor": 1,
    "country": {
      "code": "US",
      "name": "United States"
    },
    "currency": {
      "code": "usd",
      "exchangeRate": 1,
      "symbol": "$"
    }
  },
  "UY": {
    "conversionFactor": 0.7,
    "country": {
      "code": "UY",
      "name": "Uruguay"
    },
    "currency": {
      "code": "uyu",
      "exchangeRate": 42.62,
      "symbol": "$"
    }
  },
  "UZ": {
    "conversionFactor": 0.2,
    "country": {
      "code": "UZ",
      "name": "Uzbekistan"
    },
    "currency": {
      "code": "uzs",
      "exchangeRate": 12754.83,
      "symbol": "so'm"
    }
  },
  "VC": {
    "conversionFactor": 0.65,
    "country": {
      "code": "VC",
      "name": "Saint Vincent and the Grenadines"
    },
    "currency": {
      "code": "xcd",
      "exchangeRate": 2.70255,
      "symbol": "$"
    }
  },
  "VE": {
    "conversionFactor": 1,
    "country": {
      "code": "VE",
      "name": "Venezuela"
    },
    "currency": {
      "code": "ves",
      "exchangeRate": 46.55,
      "symbol": "Bs.S."
    }
  },
  "VN": {
    "conversionFactor": 0.35,
    "country": {
      "code": "VN",
      "name": "Viet Nam"
    },
    "currency": {
      "code": "vnd",
      "exchangeRate": 25412.51,
      "symbol": "₫"
    }
  },
  "VU": {
    "conversionFactor": 1,
    "country": {
      "code": "VU",
      "name": "Vanuatu"
    },
    "currency": {
      "code": "vuv",
      "exchangeRate": 121.15,
      "symbol": "Vt"
    }
  },
  "WS": {
    "conversionFactor": 0.69,
    "country": {
      "code": "WS",
      "name": "Samoa"
    },
    "currency": {
      "code": "wst",
      "exchangeRate": 2.8,
      "symbol": "T"
    }
  },
  "YE": {
    "conversionFactor": 1.75,
    "country": {
      "code": "YE",
      "name": "Yemen"
    },
    "currency": {
      "code": "yer",
      "exchangeRate": 250.349961,
      "symbol": "﷼"
    }
  },
  "ZA": {
    "conversionFactor": 0.38,
    "country": {
      "code": "ZA",
      "name": "South Africa"
    },
    "currency": {
      "code": "zar",
      "exchangeRate": 18.07,
      "symbol": "R"
    }
  },
  "ZM": {
    "conversionFactor": 0.27,
    "country": {
      "code": "ZM",
      "name": "Zambia"
    },
    "currency": {
      "code": "zmw",
      "exchangeRate": 27.63,
      "symbol": "ZK"
    }
  },
  "ZW": {
    "conversionFactor": 0.65,
    "country": {
      "code": "ZW",
      "name": "Zimbabwe"
    },
    "currency": {
      "code": "zwg",
      "exchangeRate": 25.32,
      "symbol": "$"
    }
  }
}
