{
  "description": null,
  "metadata": {
    "access": "free",
    "author": null,
    "companies": [],
    "created": 1630800000,
    "difficulty": "hard",
    "duration": 5,
    "excerpt": null,
    "featured": true,
    "format": "quiz",
    "frameworkDefault": "react",
    "frameworks": [
      {
        "framework": "react",
        "href": "/questions/quiz/what-is-reconciliation-in-react"
      }
    ],
    "href": "/questions/quiz/what-is-reconciliation-in-react",
    "importance": "high",
    "languages": [],
    "nextQuestions": [],
    "published": true,
    "ranking": 480,
    "similarQuestions": [],
    "slug": "what-is-reconciliation-in-react",
    "subtitle": null,
    "title": "React 中的协调是什么？",
    "topics": [
      "react"
    ],
    "gitHubEditUrl": "https://github.com/yangshun/top-reactjs-interview-questions/blob/main/questions/what-is-reconciliation-in-react/zh-CN.mdx"
  },
  "solution": "var Component=(()=>{var p=Object.create;var i=Object.defineProperty;var u=Object.getOwnPropertyDescriptor;var M=Object.getOwnPropertyNames;var D=Object.getPrototypeOf,R=Object.prototype.hasOwnProperty;var m=(t,n)=>()=>(n||t((n={exports:{}}).exports,n),n.exports),O=(t,n)=>{for(var c in n)i(t,c,{get:n[c],enumerable:!0})},l=(t,n,c,h)=>{if(n&&typeof n==\"object\"||typeof n==\"function\")for(let r of M(n))!R.call(t,r)&&r!==c&&i(t,r,{get:()=>n[r],enumerable:!(h=u(n,r))||h.enumerable});return t};var g=(t,n,c)=>(c=t!=null?p(D(t)):{},l(n||!t||!t.__esModule?i(c,\"default\",{value:t,enumerable:!0}):c,t)),x=t=>l(i({},\"__esModule\",{value:!0}),t);var o=m((j,a)=>{a.exports=_jsx_runtime});var v={};O(v,{default:()=>s,frontmatter:()=>f});var e=g(o()),f={title:\"React \\u4E2D\\u7684\\u534F\\u8C03\\u662F\\u4EC0\\u4E48\\uFF1F\"};function d(t){let n={a:\"a\",code:\"code\",h2:\"h2\",h3:\"h3\",hr:\"hr\",li:\"li\",ol:\"ol\",p:\"p\",pre:\"pre\",strong:\"strong\",ul:\"ul\",...t.components};return(0,e.jsxs)(e.Fragment,{children:[(0,e.jsx)(n.h2,{children:\"TL;DR\"}),`\n`,(0,e.jsx)(n.p,{children:\"React \\u4E2D\\u7684\\u534F\\u8C03\\u662F React \\u66F4\\u65B0 DOM \\u4EE5\\u5339\\u914D\\u865A\\u62DF DOM \\u7684\\u8FC7\\u7A0B\\u3002\\u5F53\\u7EC4\\u4EF6\\u7684\\u72B6\\u6001\\u6216\\u5C5E\\u6027\\u53D1\\u751F\\u53D8\\u5316\\u65F6\\uFF0CReact \\u4F1A\\u521B\\u5EFA\\u4E00\\u4E2A\\u65B0\\u7684\\u865A\\u62DF DOM \\u6811\\uFF0C\\u5E76\\u5C06\\u5176\\u4E0E\\u4E4B\\u524D\\u7684\\u6811\\u8FDB\\u884C\\u6BD4\\u8F83\\u3002\\u8FD9\\u4E2A\\u6BD4\\u8F83\\u8FC7\\u7A0B\\u79F0\\u4E3A\\u201C\\u5DEE\\u5F02\\u201D\\u3002\\u7136\\u540E\\uFF0CReact \\u53EA\\u66F4\\u65B0\\u5B9E\\u9645 DOM \\u4E2D\\u53D1\\u751F\\u53D8\\u5316\\u7684\\u90E8\\u5206\\uFF0C\\u4ECE\\u800C\\u4F7F\\u66F4\\u65B0\\u9AD8\\u6548\\u4E14\\u5FEB\\u901F\\u3002\"}),`\n`,(0,e.jsx)(n.hr,{}),`\n`,(0,e.jsx)(n.h2,{children:\"React \\u4E2D\\u7684\\u534F\\u8C03\\u662F\\u4EC0\\u4E48\\uFF1F\"}),`\n`,(0,e.jsx)(n.h3,{children:\"\\u7B80\\u4ECB\"}),`\n`,(0,e.jsx)(n.p,{children:\"\\u534F\\u8C03\\u662F React \\u4E2D\\u7684\\u4E00\\u4E2A\\u5173\\u952E\\u6982\\u5FF5\\uFF0C\\u5B83\\u5904\\u7406 React \\u5982\\u4F55\\u66F4\\u65B0 DOM \\u4EE5\\u5339\\u914D\\u865A\\u62DF DOM\\u3002\\u865A\\u62DF DOM \\u662F\\u5B9E\\u9645 DOM \\u7684\\u8F7B\\u91CF\\u7EA7\\u526F\\u672C\\uFF0CReact \\u4F7F\\u7528\\u5B83\\u6765\\u786E\\u5B9A\\u66F4\\u65B0\\u7528\\u6237\\u754C\\u9762\\u7684\\u6700\\u6709\\u6548\\u65B9\\u6CD5\\u3002\"}),`\n`,(0,e.jsx)(n.h3,{children:\"\\u865A\\u62DF DOM\"}),`\n`,(0,e.jsx)(n.p,{children:\"React \\u7EF4\\u62A4\\u4E00\\u4E2A\\u865A\\u62DF DOM \\u4EE5\\u4F18\\u5316\\u66F4\\u65B0\\u3002\\u5F53\\u7EC4\\u4EF6\\u7684\\u72B6\\u6001\\u6216\\u5C5E\\u6027\\u53D1\\u751F\\u53D8\\u5316\\u65F6\\uFF0CReact \\u4F1A\\u521B\\u5EFA\\u4E00\\u4E2A\\u65B0\\u7684\\u865A\\u62DF DOM \\u6811\\u3002\\u7136\\u540E\\u5C06\\u8FD9\\u68F5\\u65B0\\u6811\\u4E0E\\u4E4B\\u524D\\u7684\\u865A\\u62DF DOM \\u6811\\u8FDB\\u884C\\u6BD4\\u8F83\\uFF0C\\u4EE5\\u786E\\u5B9A\\u53D1\\u751F\\u4E86\\u4EC0\\u4E48\\u53D8\\u5316\\u3002\"}),`\n`,(0,e.jsx)(n.h3,{children:\"\\u5DEE\\u5F02\\u7B97\\u6CD5\"}),`\n`,(0,e.jsx)(n.p,{children:\"\\u5C06\\u65B0\\u7684\\u865A\\u62DF DOM \\u6811\\u4E0E\\u4E4B\\u524D\\u7684\\u6811\\u8FDB\\u884C\\u6BD4\\u8F83\\u7684\\u8FC7\\u7A0B\\u79F0\\u4E3A\\u201C\\u5DEE\\u5F02\\u201D\\u3002React \\u4F7F\\u7528\\u9AD8\\u5EA6\\u4F18\\u5316\\u7684\\u5DEE\\u5F02\\u7B97\\u6CD5\\u6765\\u6267\\u884C\\u6B64\\u6BD4\\u8F83\\u3002\\u8BE5\\u7B97\\u6CD5\\u7684\\u5DE5\\u4F5C\\u65B9\\u5F0F\\u5982\\u4E0B\\uFF1A\"}),`\n`,(0,e.jsxs)(n.ol,{children:[`\n`,(0,e.jsxs)(n.li,{children:[(0,e.jsx)(n.strong,{children:\"\\u5143\\u7D20\\u7C7B\\u578B\\u6BD4\\u8F83\"}),\"\\uFF1A\\u5982\\u679C\\u5143\\u7D20\\u7C7B\\u578B\\u4E0D\\u540C\\uFF0CReact \\u5C06\\u7528\\u65B0\\u5143\\u7D20\\u66FF\\u6362\\u65E7\\u5143\\u7D20\\u3002\"]}),`\n`,(0,e.jsxs)(n.li,{children:[(0,e.jsx)(n.strong,{children:\"\\u952E\\u6BD4\\u8F83\"}),\"\\uFF1A\\u5982\\u679C\\u5143\\u7D20\\u7C7B\\u578B\\u76F8\\u540C\\u4F46\\u5177\\u6709\\u4E0D\\u540C\\u7684\\u952E\\uFF0CReact \\u4F1A\\u5C06\\u5B83\\u4EEC\\u89C6\\u4E3A\\u4E0D\\u540C\\u7684\\u5143\\u7D20\\uFF0C\\u5E76\\u7528\\u65B0\\u5143\\u7D20\\u66FF\\u6362\\u65E7\\u5143\\u7D20\\u3002\"]}),`\n`,(0,e.jsxs)(n.li,{children:[(0,e.jsx)(n.strong,{children:\"\\u5C5E\\u6027\\u548C\\u72B6\\u6001\\u6BD4\\u8F83\"}),\"\\uFF1A\\u5982\\u679C\\u5143\\u7D20\\u7C7B\\u578B\\u76F8\\u540C\\u4E14\\u5177\\u6709\\u76F8\\u540C\\u7684\\u952E\\uFF0CReact \\u5C06\\u6BD4\\u8F83\\u5B83\\u4EEC\\u7684\\u5C5E\\u6027\\u548C\\u72B6\\u6001\\u4EE5\\u786E\\u5B9A\\u53D1\\u751F\\u4E86\\u4EC0\\u4E48\\u53D8\\u5316\\u3002\"]}),`\n`]}),`\n`,(0,e.jsx)(n.h3,{children:\"\\u66F4\\u65B0 DOM\"}),`\n`,(0,e.jsx)(n.p,{children:\"\\u4E00\\u65E6\\u5DEE\\u5F02\\u7B97\\u6CD5\\u786E\\u5B9A\\u4E86\\u66F4\\u6539\\uFF0CReact \\u53EA\\u4F1A\\u66F4\\u65B0\\u5B9E\\u9645 DOM \\u4E2D\\u53D1\\u751F\\u66F4\\u6539\\u7684\\u90E8\\u5206\\u3002\\u8FD9\\u4F7F\\u5F97\\u66F4\\u65B0\\u9AD8\\u6548\\u4E14\\u5FEB\\u901F\\uFF0C\\u56E0\\u4E3A React \\u907F\\u514D\\u4E86\\u91CD\\u65B0\\u6E32\\u67D3\\u6574\\u4E2A DOM\\u3002\"}),`\n`,(0,e.jsx)(n.h3,{children:\"\\u793A\\u4F8B\"}),`\n`,(0,e.jsx)(n.p,{children:\"\\u8FD9\\u662F\\u4E00\\u4E2A\\u7B80\\u5355\\u7684\\u793A\\u4F8B\\uFF0C\\u7528\\u4E8E\\u8BF4\\u660E\\u534F\\u8C03\\uFF1A\"}),`\n`,(0,e.jsx)(n.pre,{children:(0,e.jsx)(n.code,{className:\"language-jsx\",children:`class MyComponent extends React.Component {\n  constructor(props) {\n    super(props);\n    this.state = { count: 0 };\n  }\n\n  increment = () => {\n    this.setState({ count: this.state.count + 1 });\n  };\n\n  render() {\n    return (\n      <div>\n        <p>{this.state.count}</p>\n        <button onClick={this.increment}>Increment</button>\n      </div>\n    );\n  }\n}\n`})}),`\n`,(0,e.jsxs)(n.p,{children:[\"\\u5728\\u6B64\\u793A\\u4F8B\\u4E2D\\uFF0C\\u5F53\\u8C03\\u7528 \",(0,e.jsx)(n.code,{children:\"increment\"}),\" \\u65B9\\u6CD5\\u65F6\\uFF0C\\u72B6\\u6001\\u53D1\\u751F\\u53D8\\u5316\\uFF0CReact \\u4F1A\\u521B\\u5EFA\\u4E00\\u4E2A\\u65B0\\u7684\\u865A\\u62DF DOM \\u6811\\u3002\\u5DEE\\u5F02\\u7B97\\u6CD5\\u5C06\\u65B0\\u6811\\u4E0E\\u4E4B\\u524D\\u7684\\u6811\\u8FDB\\u884C\\u6BD4\\u8F83\\uFF0C\\u5E76\\u4EC5\\u4F7F\\u7528\\u65B0\\u7684\\u8BA1\\u6570 value \\u66F4\\u65B0 \",(0,e.jsx)(n.code,{children:\"<p>\"}),\" \\u5143\\u7D20\\u3002\"]}),`\n`,(0,e.jsx)(n.h2,{children:\"\\u5EF6\\u4F38\\u9605\\u8BFB\"}),`\n`,(0,e.jsxs)(n.ul,{children:[`\n`,(0,e.jsx)(n.li,{children:(0,e.jsx)(n.a,{href:\"https://react.dev/learn/preserving-and-resetting-state\",children:\"React documentation on reconciliation\"})}),`\n`,(0,e.jsx)(n.li,{children:(0,e.jsx)(n.a,{href:\"https://www.freecodecamp.org/news/what-is-the-virtual-dom-in-react/\",children:\"Understanding the virtual DOM\"})}),`\n`]})]})}function s(t={}){let{wrapper:n}=t.components||{};return n?(0,e.jsx)(n,{...t,children:(0,e.jsx)(d,{...t})}):d(t)}return x(v);})();\n;return Component;"
}