{
  "description": null,
  "metadata": {
    "access": "free",
    "author": null,
    "companies": [
      "amazon",
      "bytedance",
      "tiktok",
      "apple"
    ],
    "created": 1630800000,
    "difficulty": "medium",
    "duration": 5,
    "excerpt": null,
    "featured": true,
    "format": "quiz",
    "frameworkDefault": null,
    "frameworks": [],
    "href": "/questions/quiz/describe-the-difference-between-a-cookie-sessionstorage-and-localstorage",
    "importance": "high",
    "languages": [],
    "nextQuestions": [],
    "published": true,
    "ranking": 70,
    "similarQuestions": [],
    "slug": "describe-the-difference-between-a-cookie-sessionstorage-and-localstorage",
    "subtitle": null,
    "title": "描述浏览器中 cookie、`sessionStorage` 和 `localStorage` 之间的区别",
    "topics": [
      "web-api",
      "javascript"
    ],
    "gitHubEditUrl": "https://github.com/yangshun/top-javascript-interview-questions/blob/main/questions/describe-the-difference-between-a-cookie-sessionstorage-and-localstorage/zh-CN.mdx"
  },
  "solution": "var Component=(()=>{var s=Object.create;var i=Object.defineProperty;var g=Object.getOwnPropertyDescriptor;var S=Object.getOwnPropertyNames;var k=Object.getPrototypeOf,p=Object.prototype.hasOwnProperty;var u=(o,e)=>()=>(e||o((e={exports:{}}).exports,e),e.exports),m=(o,e)=>{for(var c in e)i(o,c,{get:e[c],enumerable:!0})},d=(o,e,c,l)=>{if(e&&typeof e==\"object\"||typeof e==\"function\")for(let r of S(e))!p.call(o,r)&&r!==c&&i(o,r,{get:()=>e[r],enumerable:!(l=g(e,r))||l.enumerable});return o};var b=(o,e,c)=>(c=o!=null?s(k(o)):{},d(e||!o||!o.__esModule?i(c,\"default\",{value:o,enumerable:!0}):c,o)),f=o=>d(i({},\"__esModule\",{value:!0}),o);var h=u((C,t)=>{t.exports=_jsx_runtime});var _={};m(_,{default:()=>I,frontmatter:()=>v});var n=b(h()),v={title:\"\\u63CF\\u8FF0\\u6D4F\\u89C8\\u5668\\u4E2D cookie\\u3001`sessionStorage` \\u548C `localStorage` \\u4E4B\\u95F4\\u7684\\u533A\\u522B\"};function a(o){let e=Object.assign({h2:\"h2\",p:\"p\",code:\"code\",a:\"a\",ul:\"ul\",li:\"li\",strong:\"strong\",table:\"table\",thead:\"thead\",tr:\"tr\",th:\"th\",tbody:\"tbody\",td:\"td\",hr:\"hr\",h3:\"h3\",pre:\"pre\"},o.components);return(0,n.jsxs)(n.Fragment,{children:[(0,n.jsx)(e.h2,{children:\"\\u603B\\u7ED3\"}),`\n`,(0,n.jsxs)(e.p,{children:[\"\\u4EE5\\u4E0B\\u90FD\\u662F\\u5728\\u5BA2\\u6237\\u7AEF\\uFF08\\u672C\\u4F8B\\u4E2D\\u4E3A\\u7528\\u6237\\u7684\\u6D4F\\u89C8\\u5668\\uFF09\\u4E0A\\u5B58\\u50A8\\u6570\\u636E\\u7684\\u673A\\u5236\\u3002\",(0,n.jsx)(e.code,{children:\"localStorage\"}),\" \\u548C \",(0,n.jsx)(e.code,{children:\"sessionStorage\"}),\" \\u90FD\\u5B9E\\u73B0\\u4E86 \",(0,n.jsx)(e.a,{href:\"https://developer.mozilla.org/en-US/docs/Web/API/Web_Storage_API\",children:\"Web Storage API \\u63A5\\u53E3\"}),\"\\u3002\"]}),`\n`,(0,n.jsxs)(e.ul,{children:[`\n`,(0,n.jsxs)(e.li,{children:[(0,n.jsx)(e.strong,{children:\"Cookies\"}),\"\\uFF1A\\u9002\\u7528\\u4E8E\\u670D\\u52A1\\u5668-\\u5BA2\\u6237\\u7AEF\\u901A\\u4FE1\\uFF0C\\u5B58\\u50A8\\u5BB9\\u91CF\\u5C0F\\uFF0C\\u53EF\\u4EE5\\u662F\\u6301\\u4E45\\u6027\\u7684\\u6216\\u57FA\\u4E8E\\u4F1A\\u8BDD\\u7684\\uFF0C\\u7279\\u5B9A\\u4E8E\\u57DF\\u3002\\u5728\\u6BCF\\u6B21\\u8BF7\\u6C42\\u65F6\\u53D1\\u9001\\u5230\\u670D\\u52A1\\u5668\\u3002\"]}),`\n`,(0,n.jsxs)(e.li,{children:[(0,n.jsx)(e.strong,{children:(0,n.jsx)(e.code,{children:\"localStorage\"})}),\"\\uFF1A\\u9002\\u7528\\u4E8E\\u957F\\u671F\\u5B58\\u50A8\\uFF0C\\u5373\\u4F7F\\u5728\\u6D4F\\u89C8\\u5668\\u5173\\u95ED\\u540E\\u6570\\u636E\\u4ECD\\u7136\\u5B58\\u5728\\uFF0C\\u53EF\\u5728\\u540C\\u4E00\\u6765\\u6E90\\u7684\\u6240\\u6709\\u9009\\u9879\\u5361\\u548C\\u7A97\\u53E3\\u4E2D\\u8BBF\\u95EE\\uFF0C\\u5728\\u4E09\\u8005\\u4E2D\\u5B58\\u50A8\\u5BB9\\u91CF\\u6700\\u9AD8\\u3002\"]}),`\n`,(0,n.jsxs)(e.li,{children:[(0,n.jsx)(e.strong,{children:(0,n.jsx)(e.code,{children:\"sessionStorage\"})}),\"\\uFF1A\\u9002\\u7528\\u4E8E\\u5355\\u4E2A\\u9875\\u9762\\u4F1A\\u8BDD\\u4E2D\\u7684\\u4E34\\u65F6\\u6570\\u636E\\uFF0C\\u5F53\\u9009\\u9879\\u5361\\u6216\\u7A97\\u53E3\\u5173\\u95ED\\u65F6\\u6570\\u636E\\u5C06\\u88AB\\u6E05\\u9664\\uFF0C\\u4E0E cookies \\u76F8\\u6BD4\\u5177\\u6709\\u66F4\\u9AD8\\u7684\\u5B58\\u50A8\\u5BB9\\u91CF\\u3002\"]}),`\n`]}),`\n`,(0,n.jsx)(e.p,{children:\"\\u4EE5\\u4E0B\\u8868\\u683C\\u603B\\u7ED3\\u4E86 3 \\u79CD\\u5BA2\\u6237\\u7AEF\\u5B58\\u50A8\\u673A\\u5236\\u3002\"}),`\n`,(0,n.jsxs)(e.table,{children:[(0,n.jsx)(e.thead,{children:(0,n.jsxs)(e.tr,{children:[(0,n.jsx)(e.th,{children:\"\\u5C5E\\u6027\"}),(0,n.jsx)(e.th,{children:\"Cookie\"}),(0,n.jsx)(e.th,{children:(0,n.jsx)(e.code,{children:\"localStorage\"})}),(0,n.jsx)(e.th,{children:(0,n.jsx)(e.code,{children:\"sessionStorage\"})})]})}),(0,n.jsxs)(e.tbody,{children:[(0,n.jsxs)(e.tr,{children:[(0,n.jsx)(e.td,{children:\"\\u53D1\\u8D77\\u8005\"}),(0,n.jsxs)(e.td,{children:[\"\\u5BA2\\u6237\\u7AEF\\u6216\\u670D\\u52A1\\u5668\\u3002\\u670D\\u52A1\\u5668\\u53EF\\u4EE5\\u4F7F\\u7528 \",(0,n.jsx)(e.code,{children:\"Set-Cookie\"}),\" \\u6807\\u5934\"]}),(0,n.jsx)(e.td,{children:\"\\u5BA2\\u6237\\u7AEF\"}),(0,n.jsx)(e.td,{children:\"\\u5BA2\\u6237\\u7AEF\"})]}),(0,n.jsxs)(e.tr,{children:[(0,n.jsx)(e.td,{children:\"\\u5BFF\\u547D\"}),(0,n.jsx)(e.td,{children:\"\\u5982\\u6307\\u5B9A\"}),(0,n.jsx)(e.td,{children:\"\\u76F4\\u5230\\u5220\\u9664\"}),(0,n.jsx)(e.td,{children:\"\\u76F4\\u5230\\u9009\\u9879\\u5361\\u5173\\u95ED\"})]}),(0,n.jsxs)(e.tr,{children:[(0,n.jsx)(e.td,{children:\"\\u662F\\u5426\\u8DE8\\u6D4F\\u89C8\\u5668\\u4F1A\\u8BDD\\u6301\\u4E45\"}),(0,n.jsx)(e.td,{children:\"\\u5982\\u679C\\u8BBE\\u7F6E\\u4E86\\u672A\\u6765\\u7684\\u8FC7\\u671F\\u65E5\\u671F\"}),(0,n.jsx)(e.td,{children:\"\\u662F\"}),(0,n.jsx)(e.td,{children:\"\\u5426\"})]}),(0,n.jsxs)(e.tr,{children:[(0,n.jsx)(e.td,{children:\"\\u662F\\u5426\\u968F\\u6BCF\\u4E2A HTTP \\u8BF7\\u6C42\\u53D1\\u9001\\u5230\\u670D\\u52A1\\u5668\"}),(0,n.jsxs)(e.td,{children:[\"\\u662F\\uFF0C\\u901A\\u8FC7 \",(0,n.jsx)(e.code,{children:\"Cookie\"}),\" \\u6807\\u5934\\u53D1\\u9001\"]}),(0,n.jsx)(e.td,{children:\"\\u5426\"}),(0,n.jsx)(e.td,{children:\"\\u5426\"})]}),(0,n.jsxs)(e.tr,{children:[(0,n.jsx)(e.td,{children:\"\\u603B\\u5BB9\\u91CF\\uFF08\\u6BCF\\u4E2A\\u57DF\\uFF09\"}),(0,n.jsx)(e.td,{children:\"4kb\"}),(0,n.jsx)(e.td,{children:\"5MB\"}),(0,n.jsx)(e.td,{children:\"5MB\"})]}),(0,n.jsxs)(e.tr,{children:[(0,n.jsx)(e.td,{children:\"\\u8BBF\\u95EE\"}),(0,n.jsx)(e.td,{children:\"\\u8DE8\\u7A97\\u53E3/\\u9009\\u9879\\u5361\"}),(0,n.jsx)(e.td,{children:\"\\u8DE8\\u7A97\\u53E3/\\u9009\\u9879\\u5361\"}),(0,n.jsx)(e.td,{children:\"\\u76F8\\u540C\\u9009\\u9879\\u5361\"})]}),(0,n.jsxs)(e.tr,{children:[(0,n.jsx)(e.td,{children:\"\\u5B89\\u5168\\u6027\"}),(0,n.jsxs)(e.td,{children:[\"JavaScript \\u65E0\\u6CD5\\u8BBF\\u95EE \",(0,n.jsx)(e.code,{children:\"HttpOnly\"}),\" cookies\"]}),(0,n.jsx)(e.td,{children:\"\\u65E0\"}),(0,n.jsx)(e.td,{children:\"\\u65E0\"})]})]})]}),`\n`,(0,n.jsx)(e.hr,{}),`\n`,(0,n.jsx)(e.h2,{children:\"Web \\u4E0A\\u7684\\u5B58\\u50A8\"}),`\n`,(0,n.jsxs)(e.p,{children:[\"Cookies\\u3001\",(0,n.jsx)(e.code,{children:\"localStorage\"}),\" \\u548C \",(0,n.jsx)(e.code,{children:\"sessionStorage\"}),\" \\u90FD\\u662F\\u5BA2\\u6237\\u7AEF\\uFF08Web \\u6D4F\\u89C8\\u5668\\uFF09\\u4E0A\\u7684\\u5B58\\u50A8\\u673A\\u5236\\u3002\\u5728\\u5BA2\\u6237\\u7AEF\\u5B58\\u50A8\\u6570\\u636E\\u5BF9\\u4E8E\\u4EC5\\u5BA2\\u6237\\u7AEF\\u7684\\u72B6\\u6001\\u5F88\\u6709\\u7528\\uFF0C\\u4F8B\\u5982\\u8BBF\\u95EE\\u4EE4\\u724C\\u3001\\u4E3B\\u9898\\u3001\\u4E2A\\u6027\\u5316\\u5E03\\u5C40\\uFF0C\\u4EE5\\u4FBF\\u7528\\u6237\\u53EF\\u4EE5\\u5728\\u8DE8\\u9009\\u9879\\u5361\\u548C\\u4F7F\\u7528\\u4F1A\\u8BDD\\u7684\\u7F51\\u7AD9\\u4E0A\\u83B7\\u5F97\\u4E00\\u81F4\\u7684\\u4F53\\u9A8C\\u3002\"]}),`\n`,(0,n.jsx)(e.p,{children:\"\\u8FD9\\u4E9B\\u5BA2\\u6237\\u7AEF\\u5B58\\u50A8\\u673A\\u5236\\u5177\\u6709\\u4EE5\\u4E0B\\u5E38\\u89C1\\u5C5E\\u6027\\uFF1A\"}),`\n`,(0,n.jsxs)(e.ul,{children:[`\n`,(0,n.jsxs)(e.li,{children:[\"\\u8FD9\\u610F\\u5473\\u7740\\u5BA2\\u6237\\u7AEF\\u53EF\\u4EE5\\u8BFB\\u53D6\\u548C\\u4FEE\\u6539\\u503C\\uFF08\",(0,n.jsx)(e.code,{children:\"HttpOnly\"}),\" cookies \\u9664\\u5916\\uFF09\\u3002\"]}),`\n`,(0,n.jsx)(e.li,{children:\"\\u57FA\\u4E8E\\u952E\\u503C\\u5BF9\\u7684\\u5B58\\u50A8\\u3002\"}),`\n`,(0,n.jsxs)(e.li,{children:[\"\\u5B83\\u4EEC\\u53EA\\u80FD\\u5C06\\u503C\\u5B58\\u50A8\\u4E3A\\u5B57\\u7B26\\u4E32\\u3002\\u975E\\u5B57\\u7B26\\u4E32\\u5FC5\\u987B\\u88AB\\u5E8F\\u5217\\u5316\\u4E3A\\u5B57\\u7B26\\u4E32\\uFF08\\u4F8B\\u5982 \",(0,n.jsx)(e.code,{children:\"JSON.stringify()\"}),\"\\uFF09\\u624D\\u80FD\\u88AB\\u5B58\\u50A8\\u3002\"]}),`\n`]}),`\n`,(0,n.jsx)(e.h3,{children:\"\\u6BCF\\u79CD\\u5B58\\u50A8\\u673A\\u5236\\u7684\\u7528\\u4F8B\"}),`\n`,(0,n.jsx)(e.p,{children:\"\\u7531\\u4E8E cookies \\u7684\\u6700\\u5927\\u5927\\u5C0F\\u76F8\\u5BF9\\u8F83\\u5C0F\\uFF0C\\u56E0\\u6B64\\u4E0D\\u5EFA\\u8BAE\\u5C06\\u6240\\u6709\\u5BA2\\u6237\\u7AEF\\u6570\\u636E\\u5B58\\u50A8\\u5728 cookies \\u4E2D\\u3002\\u5173\\u4E8E cookies \\u7684\\u663E\\u8457\\u7279\\u6027\\u662F cookies \\u4F1A\\u5728\\u6BCF\\u4E2A HTTP \\u8BF7\\u6C42\\u4E2D\\u53D1\\u9001\\u5230\\u670D\\u52A1\\u5668\\uFF0C\\u56E0\\u6B64\\u8F83\\u5C0F\\u7684\\u6700\\u5927\\u5927\\u5C0F\\u662F\\u4E00\\u4E2A\\u7279\\u6027\\uFF0C\\u53EF\\u4EE5\\u9632\\u6B62\\u60A8\\u7684 HTTP \\u8BF7\\u6C42\\u7531\\u4E8E cookies \\u800C\\u53D8\\u5F97\\u8FC7\\u5927\\u3002cookies \\u7684\\u81EA\\u52A8\\u8FC7\\u671F\\u4E5F\\u662F\\u4E00\\u4E2A\\u6709\\u7528\\u7684\\u7279\\u6027\\u3002\"}),`\n`,(0,n.jsxs)(e.p,{children:[\"\\u8003\\u8651\\u5230\\u8FD9\\u4E00\\u70B9\\uFF0C\\u6700\\u9002\\u5408\\u5B58\\u50A8\\u5728 cookies \\u4E2D\\u7684\\u6570\\u636E\\u662F\\u9700\\u8981\\u4F20\\u8F93\\u5230\\u670D\\u52A1\\u5668\\u7684\\u5C0F\\u5757\\u6570\\u636E\\uFF0C\\u4F8B\\u5982\\u8EAB\\u4EFD\\u9A8C\\u8BC1\\u4EE4\\u724C\\u3001\\u4F1A\\u8BDD ID\\u3001\\u5206\\u6790\\u8DDF\\u8E2A ID\\u3001GDPR cookie \\u540C\\u610F\\u3001\\u5BF9\\u8EAB\\u4EFD\\u9A8C\\u8BC1\\u3001\\u6388\\u6743\\u548C\\u5728\\u670D\\u52A1\\u5668\\u4E0A\\u5448\\u73B0\\u5F88\\u91CD\\u8981\\u7684\\u8BED\\u8A00\\u504F\\u597D\\u3002\\u8FD9\\u4E9B\\u503C\\u6709\\u65F6\\u5F88\\u654F\\u611F\\uFF0C\\u5E76\\u4E14\\u53EF\\u4EE5\\u4ECE cookies \\u63D0\\u4F9B\\u7684 \",(0,n.jsx)(e.code,{children:\"HttpOnly\"}),\"\\u3001\",(0,n.jsx)(e.code,{children:\"Secure\"}),\" \\u548C \",(0,n.jsx)(e.code,{children:\"Expires\"}),\"/\",(0,n.jsx)(e.code,{children:\"Max-Age\"}),\" \\u529F\\u80FD\\u4E2D\\u53D7\\u76CA\\u3002\"]}),`\n`,(0,n.jsxs)(e.p,{children:[(0,n.jsx)(e.code,{children:\"localStorage\"}),\" \\u548C \",(0,n.jsx)(e.code,{children:\"sessionStorage\"}),\" \\u90FD\\u5B9E\\u73B0\\u4E86 \",(0,n.jsx)(e.a,{href:\"https://developer.mozilla.org/en-US/docs/Web/API/Web_Storage_API\",children:\"Web Storage API \\u63A5\\u53E3\"}),\"\\u3002Web Storages \\u5177\\u6709 5MB \\u7684\\u603B\\u5BB9\\u91CF\\uFF0C\\u56E0\\u6B64\\u5B58\\u50A8\\u5927\\u5C0F\\u901A\\u5E38\\u4E0D\\u662F\\u95EE\\u9898\\u3002\\u5173\\u952E\\u7684\\u533A\\u522B\\u5728\\u4E8E\\uFF0C\\u5B58\\u50A8\\u5728 Web Storage \\u4E2D\\u7684\\u503C\\u4E0D\\u4F1A\\u81EA\\u52A8\\u968F HTTP \\u8BF7\\u6C42\\u4E00\\u8D77\\u53D1\\u9001\\u3002\"]}),`\n`,(0,n.jsxs)(e.p,{children:[\"\\u867D\\u7136\\u60A8\\u53EF\\u4EE5\\u5728\\u53D1\\u51FA AJAX/\",(0,n.jsx)(e.code,{children:\"fetch()\"}),\" \\u8BF7\\u6C42\\u65F6\\u624B\\u52A8\\u5305\\u542B\\u6765\\u81EA Web Storage \\u7684\\u503C\\uFF0C\\u4F46\\u6D4F\\u89C8\\u5668\\u4E0D\\u4F1A\\u5728\\u9875\\u9762\\u7684\\u521D\\u59CB\\u8BF7\\u6C42/\\u9996\\u6B21\\u52A0\\u8F7D\\u4E2D\\u5305\\u542B\\u5B83\\u4EEC\\u3002\\u56E0\\u6B64\\uFF0C\\u5982\\u679C\\u4F7F\\u7528\\u670D\\u52A1\\u5668\\u7AEF\\u6E32\\u67D3\\uFF08\\u901A\\u5E38\\u662F\\u4E0E\\u8EAB\\u4EFD\\u9A8C\\u8BC1/\\u6388\\u6743\\u76F8\\u5173\\u7684\\u4FE1\\u606F\\uFF09\\uFF0C\\u5219\\u4E0D\\u5E94\\u4F7F\\u7528 Web Storage \\u6765\\u5B58\\u50A8\\u670D\\u52A1\\u5668\\u7528\\u4E8E\\u9875\\u9762\\u521D\\u59CB\\u6E32\\u67D3\\u6240\\u4F9D\\u8D56\\u7684\\u6570\\u636E\\u3002\",(0,n.jsx)(e.code,{children:\"localStorage\"}),\" \\u6700\\u9002\\u5408\\u4E0D\\u5931\\u6548\\u7684\\u7528\\u6237\\u504F\\u597D\\u6570\\u636E\\uFF0C\\u4F8B\\u5982\\u4E3B\\u9898\\u548C\\u5E03\\u5C40\\uFF08\\u5982\\u679C\\u670D\\u52A1\\u5668\\u6E32\\u67D3\\u6700\\u7EC8\\u5E03\\u5C40\\u5E76\\u4E0D\\u91CD\\u8981\\uFF09\\u3002\",(0,n.jsx)(e.code,{children:\"sessionStorage\"}),\" \\u6700\\u9002\\u5408\\u53EA\\u9700\\u8981\\u5728\\u5F53\\u524D\\u6D4F\\u89C8\\u4F1A\\u8BDD\\u4E2D\\u8BBF\\u95EE\\u7684\\u4E34\\u65F6\\u6570\\u636E\\uFF0C\\u4F8B\\u5982\\u8868\\u5355\\u6570\\u636E\\uFF08\\u7528\\u4E8E\\u5728\\u610F\\u5916\\u91CD\\u65B0\\u52A0\\u8F7D\\u671F\\u95F4\\u4FDD\\u7559\\u6570\\u636E\\uFF09\\u3002\"]}),`\n`,(0,n.jsx)(e.p,{children:\"\\u4EE5\\u4E0B\\u90E8\\u5206\\u6DF1\\u5165\\u63A2\\u8BA8\\u4E86\\u6BCF\\u79CD\\u5BA2\\u6237\\u7AEF\\u5B58\\u50A8\\u673A\\u5236\\u3002\"}),`\n`,(0,n.jsx)(e.h3,{children:\"Cookies\"}),`\n`,(0,n.jsx)(e.p,{children:\"Cookies \\u7528\\u4E8E\\u5728\\u5BA2\\u6237\\u7AEF\\u5B58\\u50A8\\u5C0F\\u5757\\u6570\\u636E\\uFF0C\\u8FD9\\u4E9B\\u6570\\u636E\\u53EF\\u4EE5\\u901A\\u8FC7\\u6BCF\\u4E2A HTTP \\u8BF7\\u6C42\\u53D1\\u9001\\u56DE\\u670D\\u52A1\\u5668\\u3002\"}),`\n`,(0,n.jsxs)(e.ul,{children:[`\n`,(0,n.jsxs)(e.li,{children:[(0,n.jsx)(e.strong,{children:\"\\u5B58\\u50A8\\u5BB9\\u91CF\"}),\"\\uFF1A\\u6240\\u6709 cookies \\u9650\\u5236\\u5728 4KB \\u5DE6\\u53F3\\u3002\"]}),`\n`,(0,n.jsxs)(e.li,{children:[(0,n.jsx)(e.strong,{children:\"\\u5BFF\\u547D\"}),\"\\uFF1ACookies \\u53EF\\u4EE5\\u4F7F\\u7528 \",(0,n.jsx)(e.code,{children:\"Expires\"}),\" \\u6216 \",(0,n.jsx)(e.code,{children:\"Max-Age\"}),\" \\u5C5E\\u6027\\u8BBE\\u7F6E\\u7279\\u5B9A\\u7684\\u8FC7\\u671F\\u65E5\\u671F\\u3002\\u5982\\u679C\\u672A\\u8BBE\\u7F6E\\u8FC7\\u671F\\u65E5\\u671F\\uFF0C\\u5219\\u5728\\u6D4F\\u89C8\\u5668\\u5173\\u95ED\\u65F6\\u5220\\u9664 cookie\\uFF08\\u4F1A\\u8BDD cookie\\uFF09\\u3002\"]}),`\n`,(0,n.jsxs)(e.li,{children:[(0,n.jsx)(e.strong,{children:\"\\u8BBF\\u95EE\"}),\"\\uFF1ACookies \\u662F\\u7279\\u5B9A\\u4E8E\\u57DF\\u7684\\uFF0C\\u53EF\\u4EE5\\u5728\\u540C\\u4E00\\u57DF\\u5185\\u7684\\u4E0D\\u540C\\u9875\\u9762\\u548C\\u5B50\\u57DF\\u4E4B\\u95F4\\u5171\\u4EAB\\u3002\"]}),`\n`,(0,n.jsxs)(e.li,{children:[(0,n.jsx)(e.strong,{children:\"\\u5B89\\u5168\\u6027\"}),\"\\uFF1ACookies \\u53EF\\u4EE5\\u6807\\u8BB0\\u4E3A \",(0,n.jsx)(e.code,{children:\"HttpOnly\"}),\" \\u4EE5\\u9632\\u6B62\\u4ECE JavaScript \\u8BBF\\u95EE\\uFF0C\\u4ECE\\u800C\\u964D\\u4F4E XSS \\u653B\\u51FB\\u7684\\u98CE\\u9669\\u3002\\u5B83\\u4EEC\\u4E5F\\u53EF\\u4EE5\\u4F7F\\u7528 \",(0,n.jsx)(e.code,{children:\"Secure\"}),\" \\u6807\\u5FD7\\u8FDB\\u884C\\u4FDD\\u62A4\\uFF0C\\u4EE5\\u786E\\u4FDD\\u4EC5\\u5728\\u4F7F\\u7528 HTTPS \\u65F6\\u53D1\\u9001\\u5B83\\u4EEC\\u3002\"]}),`\n`]}),`\n`,(0,n.jsx)(e.pre,{children:(0,n.jsx)(e.code,{className:\"language-js\",children:`// Set a cookie for the name/key \\`auth_token\\` with an expiry.\ndocument.cookie =\n  'auth_token=abc123def; expires=Fri, 31 Dec 2024 23:59:59 GMT; path=/';\n\n// Read all cookies. There's no way to read specific cookies using \\`document.cookie\\`.\n// You have to parse the string yourself.\nconsole.log(document.cookie); // auth_token=abc123def\n\n// Delete the cookie with the name/key \\`auth_token\\` by setting an\n// expiry date in the past. The value doesn't matter.\ndocument.cookie = 'auth_token=; expires=Thu, 01 Jan 1970 00:00:00 GMT; path=/';\n`})}),`\n`,(0,n.jsxs)(e.p,{children:[\"\\u8BFB\\u53D6/\\u5199\\u5165 Cookie \\u662F\\u4E00\\u4EF6\\u5F88\\u75DB\\u82E6\\u7684\\u4E8B\\u60C5\\u3002\",(0,n.jsx)(e.code,{children:\"document.cookie\"}),\" \\u8FD4\\u56DE\\u4E00\\u4E2A\\u5305\\u542B\\u6240\\u6709\\u7531 \",(0,n.jsx)(e.code,{children:\";\"}),\" \\u5206\\u9694\\u7684\\u952E/\\u503C\\u5BF9\\u7684\\u5B57\\u7B26\\u4E32\\uFF0C\\u60A8\\u5FC5\\u987B\\u81EA\\u5DF1\\u89E3\\u6790\\u8BE5\\u5B57\\u7B26\\u4E32\\u3002\",(0,n.jsx)(e.a,{href:\"https://github.com/js-cookie/js-cookie\",children:(0,n.jsx)(e.code,{children:\"js-cookie\"})}),\" npm \\u5E93\\u63D0\\u4F9B\\u4E86\\u4E00\\u4E2A\\u7B80\\u5355\\u8F7B\\u91CF\\u7EA7\\u7684 API\\uFF0C\\u7528\\u4E8E\\u5728 JavaScript \\u4E2D\\u8BFB\\u5199 Cookie\\u3002\"]}),`\n`,(0,n.jsxs)(e.p,{children:[\"\\u8BBF\\u95EE Cookie \\u7684\\u73B0\\u4EE3\\u539F\\u751F\\u65B9\\u5F0F\\u662F\\u901A\\u8FC7 \",(0,n.jsx)(e.a,{href:\"https://developer.mozilla.org/en-US/docs/Web/API/Cookie_Store_API\",children:\"Cookie Store API\"}),\"\\uFF0C\\u8BE5 API \\u4EC5\\u5728 HTTPS \\u9875\\u9762\\u4E0A\\u53EF\\u7528\\u3002\"]}),`\n`,(0,n.jsx)(e.pre,{children:(0,n.jsx)(e.code,{className:\"language-js\",children:`// Set a cookie. More options are available too.\ncookieStore.set('auth_token', 'abc123def');\n\n// Async method to access a single cookie and do something with it.\ncookieStore.get('auth_token').then(...);\n\n// Async method to get all cookies.\ncookieStore.getAll().then(...);\n\n// Async method to delete a single cookie.\ncookieStore.delete('auth_token').then(() =>\n  console.log('Cookie deleted')\n);\n`})}),`\n`,(0,n.jsxs)(e.p,{children:[\"CookieStore API \\u76F8\\u5BF9\\u8F83\\u65B0\\uFF0C\\u53EF\\u80FD\\u5E76\\u975E\\u6240\\u6709\\u6D4F\\u89C8\\u5668\\u90FD\\u652F\\u6301\\uFF08\\u622A\\u81F3 2024 \\u5E74 6 \\u6708\\uFF0C\\u5728\\u6700\\u65B0\\u7684 Chrome \\u548C Edge \\u4E2D\\u53D7\\u652F\\u6301\\uFF09\\u3002\\u8BF7\\u53C2\\u9605 \",(0,n.jsx)(e.a,{href:\"https://caniuse.com/mdn-api_cookiestore\",children:\"caniuse.com\"}),\" \\u4EE5\\u83B7\\u53D6\\u6700\\u65B0\\u7684\\u517C\\u5BB9\\u6027\\u4FE1\\u606F\\u3002\"]}),`\n`,(0,n.jsx)(e.h3,{children:(0,n.jsx)(e.code,{children:\"localStorage\"})}),`\n`,(0,n.jsxs)(e.p,{children:[(0,n.jsx)(e.code,{children:\"localStorage\"}),\" \\u7528\\u4E8E\\u5B58\\u50A8\\u5373\\u4F7F\\u5728\\u6D4F\\u89C8\\u5668\\u5173\\u95ED\\u5E76\\u91CD\\u65B0\\u6253\\u5F00\\u540E\\u4ECD\\u4FDD\\u7559\\u7684\\u6570\\u636E\\u3002\\u5B83\\u4E13\\u4E3A\\u957F\\u671F\\u5B58\\u50A8\\u6570\\u636E\\u800C\\u8BBE\\u8BA1\\u3002\"]}),`\n`,(0,n.jsxs)(e.ul,{children:[`\n`,(0,n.jsxs)(e.li,{children:[(0,n.jsx)(e.strong,{children:\"\\u5B58\\u50A8\\u5BB9\\u91CF\"}),\"\\uFF1A\\u901A\\u5E38\\u6BCF\\u4E2A\\u6765\\u6E90\\u7EA6 5MB\\uFF08\\u56E0\\u6D4F\\u89C8\\u5668\\u800C\\u5F02\\uFF09\\u3002\"]}),`\n`,(0,n.jsxs)(e.li,{children:[(0,n.jsx)(e.strong,{children:\"\\u751F\\u547D\\u5468\\u671F\"}),\"\\uFF1A\",(0,n.jsx)(e.code,{children:\"localStorage\"}),\" \\u4E2D\\u7684\\u6570\\u636E\\u4F1A\\u4E00\\u76F4\\u5B58\\u5728\\uFF0C\\u76F4\\u5230\\u7528\\u6237\\u6216\\u5E94\\u7528\\u7A0B\\u5E8F\\u663E\\u5F0F\\u5220\\u9664\\u3002\"]}),`\n`,(0,n.jsxs)(e.li,{children:[(0,n.jsx)(e.strong,{children:\"\\u8BBF\\u95EE\"}),\"\\uFF1A\\u6570\\u636E\\u53EF\\u5728\\u540C\\u4E00\\u6765\\u6E90\\u7684\\u6240\\u6709\\u9009\\u9879\\u5361\\u548C\\u7A97\\u53E3\\u4E2D\\u8BBF\\u95EE\\u3002\"]}),`\n`,(0,n.jsxs)(e.li,{children:[(0,n.jsx)(e.strong,{children:\"\\u5B89\\u5168\\u6027\"}),\"\\uFF1A\\u9875\\u9762\\u4E0A\\u7684\\u6240\\u6709 JavaScript \\u90FD\\u53EF\\u4EE5\\u8BBF\\u95EE \",(0,n.jsx)(e.code,{children:\"localStorage\"}),\" \\u4E2D\\u7684\\u503C\\u3002\"]}),`\n`]}),`\n`,(0,n.jsx)(e.pre,{children:(0,n.jsx)(e.code,{className:\"language-js\",children:`// Set a value in localStorage.\nlocalStorage.setItem('key', 'value');\n\n// Get a value from localStorage.\nconsole.log(localStorage.getItem('key'));\n\n// Remove a value from localStorage.\nlocalStorage.removeItem('key');\n\n// Clear all data in localStorage.\nlocalStorage.clear();\n`})}),`\n`,(0,n.jsx)(e.h3,{children:(0,n.jsx)(e.code,{children:\"sessionStorage\"})}),`\n`,(0,n.jsxs)(e.p,{children:[(0,n.jsx)(e.code,{children:\"sessionStorage\"}),\" \\u7528\\u4E8E\\u5B58\\u50A8\\u9875\\u9762\\u4F1A\\u8BDD\\u671F\\u95F4\\u7684\\u6570\\u636E\\u3002\\u5B83\\u4E13\\u4E3A\\u4E34\\u65F6\\u5B58\\u50A8\\u6570\\u636E\\u800C\\u8BBE\\u8BA1\\u3002\"]}),`\n`,(0,n.jsxs)(e.ul,{children:[`\n`,(0,n.jsxs)(e.li,{children:[(0,n.jsx)(e.strong,{children:\"\\u5B58\\u50A8\\u5BB9\\u91CF\"}),\"\\uFF1A\\u901A\\u5E38\\u6BCF\\u4E2A\\u6765\\u6E90\\u7EA6 5MB\\uFF08\\u56E0\\u6D4F\\u89C8\\u5668\\u800C\\u5F02\\uFF09\\u3002\"]}),`\n`,(0,n.jsxs)(e.li,{children:[(0,n.jsx)(e.strong,{children:\"\\u751F\\u547D\\u5468\\u671F\"}),\"\\uFF1A\\u5F53\\u9875\\u9762\\u4F1A\\u8BDD\\u7ED3\\u675F\\u65F6\\uFF08\\u5373\\uFF0C\\u5F53\\u6D4F\\u89C8\\u5668\\u6216\\u9009\\u9879\\u5361\\u5173\\u95ED\\u65F6\\uFF09\\uFF0C\",(0,n.jsx)(e.code,{children:\"sessionStorage\"}),\" \\u4E2D\\u7684\\u6570\\u636E\\u5C06\\u88AB\\u6E05\\u9664\\u3002\\u91CD\\u65B0\\u52A0\\u8F7D\\u9875\\u9762\\u4E0D\\u4F1A\\u9500\\u6BC1 \",(0,n.jsx)(e.code,{children:\"sessionStorage\"}),\" \\u4E2D\\u7684\\u6570\\u636E\\u3002\"]}),`\n`,(0,n.jsxs)(e.li,{children:[(0,n.jsx)(e.strong,{children:\"\\u8BBF\\u95EE\"}),\"\\uFF1A\\u6570\\u636E\\u4EC5\\u5728\\u5F53\\u524D\\u9009\\u9879\\u5361\\u6216\\u7A97\\u53E3\\u4E2D\\u53EF\\u8BBF\\u95EE\\u3002\\u5177\\u6709\\u76F8\\u540C\\u9875\\u9762\\u7684\\u4E0D\\u540C\\u9009\\u9879\\u5361\\u6216\\u7A97\\u53E3\\u5C06\\u5177\\u6709\\u4E0D\\u540C\\u7684 \",(0,n.jsx)(e.code,{children:\"sessionStorage\"}),\" \\u5BF9\\u8C61\\u3002\"]}),`\n`,(0,n.jsxs)(e.li,{children:[(0,n.jsx)(e.strong,{children:\"\\u5B89\\u5168\\u6027\"}),\"\\uFF1A\\u540C\\u4E00\\u9875\\u9762\\u4E0A\\u7684\\u6240\\u6709 JavaScript \\u90FD\\u53EF\\u4EE5\\u8BBF\\u95EE\\u8BE5\\u9875\\u9762 \",(0,n.jsx)(e.code,{children:\"sessionStorage\"}),\" \\u4E2D\\u7684\\u503C\\u3002\"]}),`\n`]}),`\n`,(0,n.jsx)(e.pre,{children:(0,n.jsx)(e.code,{className:\"language-js\",children:`// Set a value in sessionStorage.\nsessionStorage.setItem('key', 'value');\n\n// Get a value from sessionStorage.\nconsole.log(sessionStorage.getItem('key'));\n\n// Remove a value from sessionStorage.\nsessionStorage.removeItem('key');\n\n// Clear all data in sessionStorage.\nsessionStorage.clear();\n`})}),`\n`,(0,n.jsx)(e.h2,{children:\"\\u6CE8\\u610F\\u4E8B\\u9879\"}),`\n`,(0,n.jsxs)(e.p,{children:[\"\\u8FD8\\u6709\\u5176\\u4ED6\\u5BA2\\u6237\\u7AEF\\u5B58\\u50A8\\u673A\\u5236\\uFF0C\\u4F8B\\u5982 \",(0,n.jsx)(e.a,{href:\"https://developer.mozilla.org/en-US/docs/Web/API/IndexedDB_API\",children:\"IndexedDB\"}),\"\\uFF0C\\u5B83\\u6BD4\\u4E0A\\u8FF0\\u6280\\u672F\\u66F4\\u5F3A\\u5927\\uFF0C\\u4F46\\u4F7F\\u7528\\u8D77\\u6765\\u66F4\\u590D\\u6742\\u3002\"]}),`\n`,(0,n.jsx)(e.h2,{children:\"\\u53C2\\u8003\"}),`\n`,(0,n.jsxs)(e.ul,{children:[`\n`,(0,n.jsx)(e.li,{children:(0,n.jsx)(e.a,{href:\"https://stackoverflow.com/questions/19867599/what-is-the-difference-between-localstorage-sessionstorage-session-and-cookies\",children:\"localStorage\\u3001sessionStorage\\u3001session \\u548C cookie \\u4E4B\\u95F4\\u6709\\u4EC0\\u4E48\\u533A\\u522B\\uFF1F\"})}),`\n`]})]})}function y(o={}){let{wrapper:e}=o.components||{};return e?(0,n.jsx)(e,Object.assign({},o,{children:(0,n.jsx)(a,o)})):a(o)}var I=y;return f(_);})();\n;return Component;"
}