{
  "description": null,
  "metadata": {
    "access": "free",
    "author": null,
    "companies": [],
    "created": 1630800000,
    "difficulty": "hard",
    "duration": 5,
    "excerpt": null,
    "featured": true,
    "format": "quiz",
    "frameworkDefault": "react",
    "frameworks": [
      {
        "framework": "react",
        "href": "/questions/quiz/what-does-re-rendering-mean-in-react"
      }
    ],
    "href": "/questions/quiz/what-does-re-rendering-mean-in-react",
    "importance": "high",
    "languages": [],
    "nextQuestions": [],
    "published": true,
    "ranking": 190,
    "similarQuestions": [],
    "slug": "what-does-re-rendering-mean-in-react",
    "subtitle": null,
    "title": "React 中重新渲染是什么意思？",
    "topics": [
      "react"
    ],
    "gitHubEditUrl": "https://github.com/yangshun/top-reactjs-interview-questions/blob/main/questions/what-does-re-rendering-mean-in-react/zh-CN.mdx"
  },
  "solution": "var Component=(()=>{var p=Object.create;var l=Object.defineProperty;var u=Object.getOwnPropertyDescriptor;var m=Object.getOwnPropertyNames;var M=Object.getPrototypeOf,D=Object.prototype.hasOwnProperty;var R=(r,n)=>()=>(n||r((n={exports:{}}).exports,n),n.exports),g=(r,n)=>{for(var c in n)l(r,c,{get:n[c],enumerable:!0})},d=(r,n,c,i)=>{if(n&&typeof n==\"object\"||typeof n==\"function\")for(let t of m(n))!D.call(r,t)&&t!==c&&l(r,t,{get:()=>n[t],enumerable:!(i=u(n,t))||i.enumerable});return r};var O=(r,n,c)=>(c=r!=null?p(M(r)):{},d(n||!r||!r.__esModule?l(c,\"default\",{value:r,enumerable:!0}):c,r)),f=r=>d(l({},\"__esModule\",{value:!0}),r);var h=R((j,o)=>{o.exports=_jsx_runtime});var x={};g(x,{default:()=>s,frontmatter:()=>C});var e=O(h()),C={title:\"React \\u4E2D\\u91CD\\u65B0\\u6E32\\u67D3\\u662F\\u4EC0\\u4E48\\u610F\\u601D\\uFF1F\"};function a(r){let n={a:\"a\",code:\"code\",h2:\"h2\",h3:\"h3\",hr:\"hr\",li:\"li\",ol:\"ol\",p:\"p\",pre:\"pre\",strong:\"strong\",ul:\"ul\",...r.components};return(0,e.jsxs)(e.Fragment,{children:[(0,e.jsx)(n.h2,{children:\"\\u603B\\u7ED3\"}),`\n`,(0,e.jsx)(n.p,{children:\"\\u5728 React \\u4E2D\\uFF0C\\u91CD\\u65B0\\u6E32\\u67D3\\u662F\\u6307\\u7EC4\\u4EF6\\u54CD\\u5E94\\u72B6\\u6001\\u6216 props \\u7684\\u53D8\\u5316\\u800C\\u66F4\\u65B0\\u5176\\u5728 DOM \\u4E2D\\u7684\\u8F93\\u51FA\\u7684\\u8FC7\\u7A0B\\u3002\\u5F53\\u7EC4\\u4EF6\\u7684\\u72B6\\u6001\\u6216 props \\u53D1\\u751F\\u53D8\\u5316\\u65F6\\uFF0CReact \\u4F1A\\u89E6\\u53D1\\u91CD\\u65B0\\u6E32\\u67D3\\uFF0C\\u4EE5\\u786E\\u4FDD UI \\u53CD\\u6620\\u6700\\u65B0\\u7684\\u6570\\u636E\\u3002\\u6B64\\u8FC7\\u7A0B\\u6D89\\u53CA\\u518D\\u6B21\\u8C03\\u7528\\u7EC4\\u4EF6\\u7684 render \\u65B9\\u6CD5\\u4EE5\\u751F\\u6210\\u65B0\\u7684\\u865A\\u62DF DOM\\uFF0C\\u7136\\u540E\\u5C06\\u5176\\u4E0E\\u4E4B\\u524D\\u7684\\u865A\\u62DF DOM \\u8FDB\\u884C\\u6BD4\\u8F83\\uFF0C\\u4EE5\\u786E\\u5B9A\\u66F4\\u65B0\\u5B9E\\u9645 DOM \\u6240\\u9700\\u7684\\u6700\\u5C0F\\u66F4\\u6539\\u96C6\\u3002\"}),`\n`,(0,e.jsx)(n.hr,{}),`\n`,(0,e.jsx)(n.h2,{children:\"React \\u4E2D\\u91CD\\u65B0\\u6E32\\u67D3\\u662F\\u4EC0\\u4E48\\u610F\\u601D\\uFF1F\"}),`\n`,(0,e.jsx)(n.h3,{children:\"\\u7406\\u89E3\\u91CD\\u65B0\\u6E32\\u67D3\"}),`\n`,(0,e.jsx)(n.p,{children:\"\\u5728 React \\u4E2D\\uFF0C\\u91CD\\u65B0\\u6E32\\u67D3\\u662F\\u6307\\u7EC4\\u4EF6\\u54CD\\u5E94\\u5176\\u72B6\\u6001\\u6216 props \\u7684\\u53D8\\u5316\\u800C\\u66F4\\u65B0\\u5176\\u5728 DOM \\u4E2D\\u7684\\u8F93\\u51FA\\u7684\\u8FC7\\u7A0B\\u3002\\u8FD9\\u786E\\u4FDD\\u4E86 UI \\u59CB\\u7EC8\\u4E0E\\u5E95\\u5C42\\u6570\\u636E\\u540C\\u6B65\\u3002\"}),`\n`,(0,e.jsx)(n.h3,{children:\"\\u4EC0\\u4E48\\u65F6\\u5019\\u4F1A\\u53D1\\u751F\\u91CD\\u65B0\\u6E32\\u67D3\\uFF1F\"}),`\n`,(0,e.jsx)(n.p,{children:\"\\u91CD\\u65B0\\u6E32\\u67D3\\u53D1\\u751F\\u5728\\u4EE5\\u4E0B\\u60C5\\u51B5\\u4E0B\\uFF1A\"}),`\n`,(0,e.jsxs)(n.ul,{children:[`\n`,(0,e.jsxs)(n.li,{children:[\"\\u5F53\\u7EC4\\u4EF6\\u4F7F\\u7528 \",(0,e.jsx)(n.code,{children:\"setState\"}),\" \\u66F4\\u6539\\u72B6\\u6001\\u65F6\"]}),`\n`,(0,e.jsx)(n.li,{children:\"\\u5F53\\u7EC4\\u4EF6\\u4ECE\\u5176\\u7236\\u7EC4\\u4EF6\\u63A5\\u6536\\u5230\\u65B0\\u7684 props \\u65F6\"}),`\n`,(0,e.jsx)(n.li,{children:\"\\u5F53\\u7236\\u7EC4\\u4EF6\\u91CD\\u65B0\\u6E32\\u67D3\\u65F6\\uFF0C\\u5BFC\\u81F4\\u5176\\u5B50\\u7EC4\\u4EF6\\u4E5F\\u91CD\\u65B0\\u6E32\\u67D3\"}),`\n`]}),`\n`,(0,e.jsx)(n.h3,{children:\"\\u91CD\\u65B0\\u6E32\\u67D3\\u8FC7\\u7A0B\"}),`\n`,(0,e.jsxs)(n.ol,{children:[`\n`,(0,e.jsxs)(n.li,{children:[(0,e.jsx)(n.strong,{children:\"\\u72B6\\u6001\\u6216 props \\u66F4\\u6539\"}),\"\\uFF1A\\u5F53\\u7EC4\\u4EF6\\u7684\\u72B6\\u6001\\u6216 props \\u66F4\\u6539\\u65F6\\uFF0CReact \\u4F1A\\u4E3A\\u8BE5\\u7EC4\\u4EF6\\u5B89\\u6392\\u91CD\\u65B0\\u6E32\\u67D3\\u3002\"]}),`\n`,(0,e.jsxs)(n.li,{children:[(0,e.jsx)(n.strong,{children:\"render \\u65B9\\u6CD5\"}),\"\\uFF1AReact \\u8C03\\u7528\\u7EC4\\u4EF6\\u7684 \",(0,e.jsx)(n.code,{children:\"render\"}),\" \\u65B9\\u6CD5\\u4EE5\\u751F\\u6210\\u65B0\\u7684\\u865A\\u62DF DOM \\u6811\\u3002\"]}),`\n`,(0,e.jsxs)(n.li,{children:[(0,e.jsx)(n.strong,{children:\"\\u865A\\u62DF DOM \\u6BD4\\u8F83\"}),\"\\uFF1AReact \\u4F7F\\u7528 diffing \\u7B97\\u6CD5\\u5C06\\u65B0\\u7684\\u865A\\u62DF DOM \\u6811\\u4E0E\\u4E4B\\u524D\\u7684\\u865A\\u62DF DOM \\u6811\\u8FDB\\u884C\\u6BD4\\u8F83\\u3002\"]}),`\n`,(0,e.jsxs)(n.li,{children:[(0,e.jsx)(n.strong,{children:\"DOM \\u66F4\\u65B0\"}),\"\\uFF1AReact \\u8BA1\\u7B97\\u6240\\u9700\\u7684\\u6700\\u5C0F\\u66F4\\u6539\\u96C6\\u5E76\\u76F8\\u5E94\\u5730\\u66F4\\u65B0\\u5B9E\\u9645 DOM\\u3002\"]}),`\n`]}),`\n`,(0,e.jsx)(n.h3,{children:\"\\u793A\\u4F8B\"}),`\n`,(0,e.jsx)(n.p,{children:\"\\u8FD9\\u662F\\u4E00\\u4E2A\\u7B80\\u5355\\u7684\\u793A\\u4F8B\\uFF0C\\u7528\\u4E8E\\u8BF4\\u660E\\u91CD\\u65B0\\u6E32\\u67D3\\uFF1A\"}),`\n`,(0,e.jsx)(n.pre,{children:(0,e.jsx)(n.code,{className:\"language-jsx\",children:`import React, { useState } from 'react';\n\nfunction Counter() {\n  const [count, setCount] = useState(0);\n\n  return (\n    <div>\n      <p>Count: {count}</p>\n      <button onClick={() => setCount(count + 1)}>Increment</button>\n    </div>\n  );\n}\n`})}),`\n`,(0,e.jsx)(n.p,{children:\"\\u5728\\u6B64\\u793A\\u4F8B\\u4E2D\\uFF1A\"}),`\n`,(0,e.jsxs)(n.ul,{children:[`\n`,(0,e.jsxs)(n.li,{children:[(0,e.jsx)(n.code,{children:\"Counter\"}),\" \\u7EC4\\u4EF6\\u6709\\u4E00\\u4E2A\\u72B6\\u6001\\u53D8\\u91CF \",(0,e.jsx)(n.code,{children:\"count\"}),\"\\u3002\"]}),`\n`,(0,e.jsxs)(n.li,{children:[\"\\u5F53\\u5355\\u51FB\\u6309\\u94AE\\u65F6\\uFF0C\",(0,e.jsx)(n.code,{children:\"setCount\"}),\" \\u4F1A\\u66F4\\u65B0\\u72B6\\u6001\\uFF0C\\u4ECE\\u800C\\u89E6\\u53D1\\u91CD\\u65B0\\u6E32\\u67D3\\u3002\"]}),`\n`,(0,e.jsxs)(n.li,{children:[\"\\u518D\\u6B21\\u8C03\\u7528 \",(0,e.jsx)(n.code,{children:\"render\"}),\" \\u65B9\\u6CD5\\uFF0C\\u5E76\\u5C06\\u65B0\\u7684\\u865A\\u62DF DOM \\u4E0E\\u4E4B\\u524D\\u7684\\u865A\\u62DF DOM \\u8FDB\\u884C\\u6BD4\\u8F83\\u3002\"]}),`\n`,(0,e.jsx)(n.li,{children:\"React \\u66F4\\u65B0\\u5B9E\\u9645 DOM \\u4EE5\\u53CD\\u6620\\u65B0\\u7684\\u8BA1\\u6570\\u3002\"}),`\n`]}),`\n`,(0,e.jsx)(n.h3,{children:\"\\u6027\\u80FD\\u8003\\u8651\"}),`\n`,(0,e.jsx)(n.p,{children:\"\\u91CD\\u65B0\\u6E32\\u67D3\\u53EF\\u80FD\\u5F88\\u6602\\u8D35\\uFF0C\\u5C24\\u5176\\u5BF9\\u4E8E\\u590D\\u6742\\u7684\\u7EC4\\u4EF6\\u6216\\u5927\\u578B\\u5E94\\u7528\\u7A0B\\u5E8F\\u800C\\u8A00\\u3002\\u4E3A\\u4E86\\u4F18\\u5316\\u6027\\u80FD\\uFF0CReact \\u63D0\\u4F9B\\u4E86\\u51E0\\u79CD\\u6280\\u672F\\uFF1A\"}),`\n`,(0,e.jsxs)(n.ul,{children:[`\n`,(0,e.jsxs)(n.li,{children:[(0,e.jsx)(n.strong,{children:\"PureComponent\"}),\"\\uFF1A\\u4E00\\u4E2A\\u57FA\\u7C7B\\uFF0C\\u5B83\\u5B9E\\u73B0\\u4E86 props \\u548C state \\u7684\\u6D45\\u5C42\\u6BD4\\u8F83\\uFF0C\\u4EE5\\u9632\\u6B62\\u4E0D\\u5FC5\\u8981\\u7684\\u91CD\\u65B0\\u6E32\\u67D3\\u3002\"]}),`\n`,(0,e.jsxs)(n.li,{children:[(0,e.jsx)(n.strong,{children:\"React.memo\"}),\"\\uFF1A\\u4E00\\u4E2A\\u9AD8\\u9636\\u7EC4\\u4EF6\\uFF0C\\u5B83\\u4F1A\\u8BB0\\u5FC6\\u7EC4\\u4EF6 render \\u7684\\u7ED3\\u679C\\uFF0C\\u4EE5\\u907F\\u514D\\u5728 props \\u672A\\u66F4\\u6539\\u7684\\u60C5\\u51B5\\u4E0B\\u91CD\\u65B0\\u6E32\\u67D3\\u3002\"]}),`\n`,(0,e.jsxs)(n.li,{children:[(0,e.jsx)(n.strong,{children:\"useMemo \\u548C useCallback\"}),\"\\uFF1A\\u7528\\u4E8E\\u8BB0\\u5FC6\\u503C\\u548C\\u51FD\\u6570\\u7684 Hook\\uFF0C\\u4EE5\\u9632\\u6B62\\u4E0D\\u5FC5\\u8981\\u7684\\u91CD\\u65B0\\u6E32\\u67D3\\u3002\"]}),`\n`]}),`\n`,(0,e.jsx)(n.h2,{children:\"\\u5EF6\\u4F38\\u9605\\u8BFB\"}),`\n`,(0,e.jsxs)(n.ul,{children:[`\n`,(0,e.jsx)(n.li,{children:(0,e.jsx)(n.a,{href:\"https://react.dev/learn/render-and-commit\",children:\"React documentation on rendering\"})}),`\n`,(0,e.jsx)(n.li,{children:(0,e.jsx)(n.a,{href:\"https://react.dev/learn/state-a-components-memory\",children:\"React documentation on state\"})}),`\n`,(0,e.jsx)(n.li,{children:(0,e.jsx)(n.a,{href:\"https://react.dev/reference/react/memo\",children:\"React.memo\"})}),`\n`]})]})}function s(r={}){let{wrapper:n}=r.components||{};return n?(0,e.jsx)(n,{...r,children:(0,e.jsx)(a,{...r})}):a(r)}return f(x);})();\n;return Component;"
}