{
  "access": "premium",
  "author": null,
  "companies": [],
  "created": 1683331200,
  "difficulty": "easy",
  "duration": 5,
  "featured": false,
  "format": "javascript",
  "frameworkDefault": null,
  "frameworks": [],
  "href": "/questions/javascript/number-of-arguments",
  "importance": "low",
  "languages": [
    "js",
    "ts"
  ],
  "nextQuestions": [
    "classnames",
    "curry"
  ],
  "published": true,
  "ranking": 100,
  "similarQuestions": [
    "function-length"
  ],
  "slug": "number-of-arguments",
  "subtitle": null,
  "topics": []
}