{
  "description": null,
  "metadata": {
    "access": "free",
    "author": null,
    "companies": [],
    "created": 1630800000,
    "difficulty": "medium",
    "duration": 5,
    "excerpt": null,
    "featured": false,
    "format": "quiz",
    "frameworkDefault": null,
    "frameworks": [],
    "href": "/questions/quiz/what-are-some-of-the-gotchas-for-writing-efficient-css",
    "importance": "low",
    "languages": [],
    "nextQuestions": [],
    "published": true,
    "ranking": 100,
    "similarQuestions": [],
    "slug": "what-are-some-of-the-gotchas-for-writing-efficient-css",
    "subtitle": null,
    "title": "编写高效 CSS 时需要注意哪些“陷阱”？",
    "topics": [
      "css"
    ],
    "gitHubEditUrl": "https://github.com/yangshun/front-end-interview-handbook/blob/main/packages/quiz/questions/what-are-some-of-the-gotchas-for-writing-efficient-css/zh-CN.mdx"
  },
  "solution": "var Component=(()=>{var l=Object.create;var c=Object.defineProperty;var d=Object.getOwnPropertyDescriptor;var p=Object.getOwnPropertyNames;var f=Object.getPrototypeOf,x=Object.prototype.hasOwnProperty;var j=(n,t)=>()=>(t||n((t={exports:{}}).exports,t),t.exports),u=(n,t)=>{for(var r in t)c(n,r,{get:t[r],enumerable:!0})},i=(n,t,r,o)=>{if(t&&typeof t==\"object\"||typeof t==\"function\")for(let s of p(t))!x.call(n,s)&&s!==r&&c(n,s,{get:()=>t[s],enumerable:!(o=d(t,s))||o.enumerable});return n};var _=(n,t,r)=>(r=n!=null?l(f(n)):{},i(t||!n||!n.__esModule?c(r,\"default\",{value:n,enumerable:!0}):r,n)),g=n=>i(c({},\"__esModule\",{value:!0}),n);var m=j((O,a)=>{a.exports=_jsx_runtime});var b={};u(b,{default:()=>S,frontmatter:()=>M});var e=_(m()),M={title:\"\\u7F16\\u5199\\u9AD8\\u6548 CSS \\u65F6\\u9700\\u8981\\u6CE8\\u610F\\u54EA\\u4E9B\\u201C\\u9677\\u9631\\u201D\\uFF1F\"};function h(n){let t=Object.assign({p:\"p\",a:\"a\"},n.components);return(0,e.jsxs)(e.Fragment,{children:[(0,e.jsx)(t.p,{children:\"\\u9996\\u5148\\uFF0C\\u4E86\\u89E3\\u6D4F\\u89C8\\u5668\\u4ECE\\u6700\\u53F3\\u4FA7\\uFF08\\u5173\\u952E\\u9009\\u62E9\\u5668\\uFF09\\u5230\\u5DE6\\u4FA7\\u5339\\u914D\\u9009\\u62E9\\u5668\\u3002 \\u6D4F\\u89C8\\u5668\\u6839\\u636E\\u5173\\u952E\\u9009\\u62E9\\u5668\\u8FC7\\u6EE4 DOM \\u4E2D\\u7684\\u5143\\u7D20\\uFF0C\\u5E76\\u904D\\u5386\\u5176\\u7236\\u5143\\u7D20\\u4EE5\\u786E\\u5B9A\\u5339\\u914D\\u9879\\u3002 \\u9009\\u62E9\\u5668\\u94FE\\u7684\\u957F\\u5EA6\\u8D8A\\u77ED\\uFF0C\\u6D4F\\u89C8\\u5668\\u786E\\u5B9A\\u8BE5\\u5143\\u7D20\\u662F\\u5426\\u4E0E\\u9009\\u62E9\\u5668\\u5339\\u914D\\u7684\\u901F\\u5EA6\\u5C31\\u8D8A\\u5FEB\\u3002 \\u56E0\\u6B64\\uFF0C\\u907F\\u514D\\u4F7F\\u7528\\u6807\\u7B7E\\u548C\\u901A\\u7528\\u9009\\u62E9\\u5668\\u4F5C\\u4E3A\\u5173\\u952E\\u9009\\u62E9\\u5668\\u3002 \\u5B83\\u4EEC\\u5339\\u914D\\u5927\\u91CF\\u5143\\u7D20\\uFF0C\\u6D4F\\u89C8\\u5668\\u5C06\\u4E0D\\u5F97\\u4E0D\\u505A\\u66F4\\u591A\\u7684\\u5DE5\\u4F5C\\u6765\\u786E\\u5B9A\\u7236\\u5143\\u7D20\\u662F\\u5426\\u5339\\u914D\\u3002\"}),`\n`,(0,e.jsxs)(t.p,{children:[(0,e.jsx)(t.a,{href:\"https://bem.info/\",children:\"BEM (Block Element Modifier)\"}),\" \\u65B9\\u6CD5\\u5EFA\\u8BAE\\u6240\\u6709\\u5185\\u5BB9\\u90FD\\u4F7F\\u7528\\u5355\\u4E2A\\u7C7B\\uFF0C\\u5E76\\u4E14\\u5728\\u9700\\u8981\\u5C42\\u6B21\\u7ED3\\u6784\\u65F6\\uFF0C\\u5C06\\u5176\\u4E5F\\u878D\\u5165\\u5230\\u7C7B\\u7684\\u540D\\u79F0\\u4E2D\\uFF0C\\u8FD9\\u81EA\\u7136\\u4F7F\\u9009\\u62E9\\u5668\\u9AD8\\u6548\\u4E14\\u6613\\u4E8E\\u8986\\u76D6\\u3002\"]}),`\n`,(0,e.jsxs)(t.p,{children:[\"\\u6CE8\\u610F\\u54EA\\u4E9B CSS \\u5C5E\\u6027\\u4F1A\",(0,e.jsx)(t.a,{href:\"https://csstriggers.com/\",children:\"\\u89E6\\u53D1\"}),\"\\u56DE\\u6D41\\u3001\\u91CD\\u7ED8\\u548C\\u5408\\u6210\\u3002 \\u5C3D\\u53EF\\u80FD\\u907F\\u514D\\u7F16\\u5199\\u66F4\\u6539\\u5E03\\u5C40\\uFF08\\u89E6\\u53D1\\u56DE\\u6D41\\uFF09\\u7684\\u6837\\u5F0F\\u3002\"]})]})}function C(n={}){let{wrapper:t}=n.components||{};return t?(0,e.jsx)(t,Object.assign({},n,{children:(0,e.jsx)(h,n)})):h(n)}var S=C;return g(b);})();\n;return Component;"
}