{
  "description": "var Component=(()=>{var d=Object.create;var a=Object.defineProperty;var m=Object.getOwnPropertyDescriptor;var u=Object.getOwnPropertyNames;var p=Object.getPrototypeOf,g=Object.prototype.hasOwnProperty;var f=(r,e)=>()=>(e||r((e={exports:{}}).exports,e),e.exports),y=(r,e)=>{for(var n in e)a(r,n,{get:e[n],enumerable:!0})},o=(r,e,n,s)=>{if(e&&typeof e==\"object\"||typeof e==\"function\")for(let i of u(e))!g.call(r,i)&&i!==n&&a(r,i,{get:()=>e[i],enumerable:!(s=m(e,i))||s.enumerable});return r};var x=(r,e,n)=>(n=r!=null?d(p(r)):{},o(e||!r||!r.__esModule?a(n,\"default\",{value:r,enumerable:!0}):n,r)),v=r=>o(a({},\"__esModule\",{value:!0}),r);var h=f((S,c)=>{c.exports=_jsx_runtime});var M={};y(M,{default:()=>w,frontmatter:()=>b});var t=x(h()),b={title:\"Merge Sort\",excerpt:\"Implement a function that performs a recursive merge sort\"};function l(r){let e=Object.assign({p:\"p\",img:\"img\",h2:\"h2\",pre:\"pre\",code:\"code\"},r.components);return(0,t.jsxs)(t.Fragment,{children:[(0,t.jsx)(e.p,{children:\"Implement a function that performs a recursive merge sort. The function should be recursive and takes in an array of integers. The output should be an array with the input sorted in ascending order.\"}),`\n`,(0,t.jsx)(e.p,{children:(0,t.jsx)(e.img,{src:\"/img/questions/merge-sort/merge-sort-input-output.png\",alt:\"Recursive Merge Sort expected input and output\"})}),`\n`,(0,t.jsx)(e.h2,{children:\"Examples\"}),`\n`,(0,t.jsx)(e.pre,{children:(0,t.jsx)(e.code,{className:\"language-js\",children:`mergeSort([9, 3, 6, 2, 1, 11]); // [1, 2, 3, 6, 9, 11]\nmergeSort([12, 16, 14, 1, 2, 3]); // [1, 2, 3, 12, 14, 16]\n`})}),`\n`,(0,t.jsx)(e.h2,{children:\"Recap\"}),`\n`,(0,t.jsxs)(e.p,{children:[\"Merge sort is a recursive algorithm that divides and conquers - it continuously divides the input array into two halves until it cannot be further divided (i.e. reaches the base case of array \",(0,t.jsx)(e.code,{children:\"<=\"}),' 1 element(s) - which by definition, is sorted). The \"merge\" section of the algorithm then repeatedly merges individually sorted subarrays into larger arrays until the entire array is merged.']}),`\n`,(0,t.jsx)(e.p,{children:\"The merging process involves creating a new empty array and repeatedly taking the smallest element from either the first or second half. When one half is empty, we append all elements from the other half to the new array and return it.\"}),`\n`,(0,t.jsx)(e.p,{children:(0,t.jsx)(e.img,{src:\"/img/questions/merge-sort/merge-sort-explanation.png\",alt:\"Recursive Merge Sort explanation\"})})]})}function j(r={}){let{wrapper:e}=r.components||{};return e?(0,t.jsx)(e,Object.assign({},r,{children:(0,t.jsx)(l,r)})):l(r)}var w=j;return v(M);})();\n;return Component;",
  "files": {
    "/package.json": "{\n  \"name\": \"@gfe-questions/merge-sort\",\n  \"version\": \"0.0.1\",\n  \"main\": \"/src/merge-sort.ts\",\n  \"devDependencies\": {\n    \"@types/jest\": \"29.5.0\",\n    \"typescript\": \"5.0.2\"\n  }\n}\n",
    "/tsconfig.json": "{\n  \"include\": [\"./**/*\"],\n  \"compilerOptions\": {\n    \"target\": \"es2020\",\n    \"strict\": true,\n    \"esModuleInterop\": true,\n    \"lib\": [\"dom\", \"dom.iterable\", \"esnext\"],\n    \"jsx\": \"react-jsx\"\n  }\n}\n",
    "/src/merge-sort.run.test.ts": "import mergeSort from './merge-sort';\n\ndescribe('mergeSort', () => {\n  test('empty', () => {\n    expect(mergeSort([])).toEqual([]);\n  });\n\n  test('one element', () => {\n    expect(mergeSort([1])).toEqual([1]);\n  });\n\n  test('two elements', () => {\n    expect(mergeSort([2, 1])).toEqual([1, 2]);\n    expect(mergeSort([1, 2])).toEqual([1, 2]);\n  });\n});\n",
    "/src/merge-sort.submit.test.ts": "import mergeSort from './merge-sort';\n\ndescribe('mergeSort', () => {\n  test('empty', () => {\n    expect(mergeSort([])).toEqual([]);\n  });\n\n  test('one element', () => {\n    expect(mergeSort([1])).toEqual([1]);\n  });\n\n  test('two elements', () => {\n    expect(mergeSort([2, 1])).toEqual([1, 2]);\n    expect(mergeSort([1, 2])).toEqual([1, 2]);\n  });\n\n  test('more than two elements', () => {\n    expect(mergeSort([10, 2, 4])).toEqual([2, 4, 10]);\n    expect(mergeSort([4, 5, 6, 1, 2, 3])).toEqual([1, 2, 3, 4, 5, 6]);\n    expect(mergeSort([1, 2, 3, 4, 5, 0])).toEqual([0, 1, 2, 3, 4, 5]);\n    expect(mergeSort([10, 9, 8, 7, 6, 5, 4, 3, 2, 1])).toEqual([\n      1, 2, 3, 4, 5, 6, 7, 8, 9, 10,\n    ]);\n    expect(mergeSort([5, 4, 3, 2, 1, 10, 9, 8, 7, 6])).toEqual([\n      1, 2, 3, 4, 5, 6, 7, 8, 9, 10,\n    ]);\n    expect(mergeSort([98322, 3242, 876, -234, 34, 12331])).toEqual([\n      -234, 34, 876, 3242, 12331, 98322,\n    ]);\n  });\n\n  test('duplicate elements', () => {\n    expect(mergeSort([1, 1])).toEqual([1, 1]);\n    expect(mergeSort([2, 2, 2])).toEqual([2, 2, 2]);\n    expect(mergeSort([2, 1, 2])).toEqual([1, 2, 2]);\n    expect(mergeSort([1, 1, 1, 1, 1, 1])).toEqual([1, 1, 1, 1, 1, 1]);\n    expect(mergeSort([7, 2, 4, 3, 1, 2])).toEqual([1, 2, 2, 3, 4, 7]);\n  });\n});\n",
    "/src/merge-sort.ts": "export default function mergeSort(arr: Array<number>): Array<number> {\n  // Return if array only has 0 or 1 elements (base case).\n  if (arr.length <= 1) {\n    return arr;\n  }\n\n  // Divide the array into two.\n  const midPoint = Math.floor(arr.length / 2);\n  const left = arr.slice(0, midPoint);\n  const right = arr.slice(midPoint);\n\n  // Merge sort each half recursively.\n  const sortedLeft = mergeSort(left);\n  const sortedRight = mergeSort(right);\n\n  // Merge sorted halves.\n  return merge(sortedLeft, sortedRight);\n}\n\n/**\n * Merges two sorted arrays of elements into one.\n */\nfunction merge(left: Array<number>, right: Array<number>): Array<number> {\n  // Create an empty array to store the merged result.\n  const mergedResult = [];\n\n  let l = 0;\n  let r = 0;\n  // Repeatedly compare smallest element from each half\n  // and append it to the merged result.\n  // When one half runs out of elements,\n  // append all the elements of the remaining half to the merged array\n  while (l < left.length && r < right.length) {\n    if (left[l] < right[r]) {\n      mergedResult.push(left[l]);\n      l++;\n    } else {\n      mergedResult.push(right[r]);\n      r++;\n    }\n  }\n\n  // Append any remaining elements from each sides.\n  mergedResult.push(...left.slice(l), ...right.slice(r));\n  return mergedResult;\n}\n"
  },
  "info": {
    "excerpt": "Implement a function that performs a recursive merge sort",
    "title": "Merge Sort"
  },
  "metadata": {
    "access": "free",
    "author": null,
    "companies": [],
    "created": 1671667200,
    "difficulty": "medium",
    "duration": 20,
    "featured": false,
    "format": "algo",
    "frameworkDefault": null,
    "frameworks": [],
    "href": "/questions/algo/merge-sort",
    "importance": "low",
    "languages": [
      "js",
      "ts"
    ],
    "nextQuestions": [],
    "published": true,
    "ranking": 100,
    "similarQuestions": [
      "quick-sort"
    ],
    "slug": "merge-sort",
    "subtitle": null,
    "topics": [
      "sorting"
    ]
  },
  "skeleton": {
    "js": "/**\n * @param {Array<number>} arr The input integer array to be sorted.\n * @return {Array<number>}\n */\nexport default function recursiveMergeSort(arr) {\n  throw 'Not implemented!';\n}",
    "ts": "export default function recursiveMergeSort(arr: Array<number>): Array<number> {\n  throw 'Not implemented!';\n}"
  },
  "solution": "var Component=(()=>{var u=Object.create;var i=Object.defineProperty;var f=Object.getOwnPropertyDescriptor;var p=Object.getOwnPropertyNames;var y=Object.getPrototypeOf,b=Object.prototype.hasOwnProperty;var x=(t,e)=>()=>(e||t((e={exports:{}}).exports,e),e.exports),v=(t,e)=>{for(var n in e)i(t,n,{get:e[n],enumerable:!0})},s=(t,e,n,o)=>{if(e&&typeof e==\"object\"||typeof e==\"function\")for(let a of p(e))!b.call(t,a)&&a!==n&&i(t,a,{get:()=>e[a],enumerable:!(o=f(e,a))||o.enumerable});return t};var w=(t,e,n)=>(n=t!=null?u(y(t)):{},s(e||!t||!t.__esModule?i(n,\"default\",{value:t,enumerable:!0}):n,t)),R=t=>s(i({},\"__esModule\",{value:!0}),t);var h=x((C,l)=>{l.exports=_jsx_runtime});var j={};v(j,{default:()=>O});var r=w(h());var d=MDXCodeBlock;var m=`/**\n * @param {Array<number>} arr The input integer array to be sorted.\n * @return {Array<number>}\n */\nexport default function mergeSort(arr) {\n  // Return if array only has 0 or 1 elements (base case).\n  if (arr.length <= 1) {\n    return arr;\n  }\n\n  // Divide the array into two.\n  const midPoint = Math.floor(arr.length / 2);\n  const left = arr.slice(0, midPoint);\n  const right = arr.slice(midPoint);\n\n  // Merge sort each half recursively.\n  const sortedLeft = mergeSort(left);\n  const sortedRight = mergeSort(right);\n\n  // Merge sorted halves.\n  return merge(sortedLeft, sortedRight);\n}\n\n/**\n * Merges two sorted arrays of elements into one.\n * @param {Array<number>} left\n * @param {Array<number>} right\n * @return {Array<number>}\n */\nfunction merge(left, right) {\n  // Create an empty array to store the merged result.\n  const mergedResult = [];\n\n  let l = 0;\n  let r = 0;\n  // Repeatedly compare smallest element from each half\n  // and append it to the merged result.\n  // When one half runs out of elements,\n  // append all the elements of the remaining half to the merged array\n  while (l < left.length && r < right.length) {\n    if (left[l] < right[r]) {\n      mergedResult.push(left[l]);\n      l++;\n    } else {\n      mergedResult.push(right[r]);\n      r++;\n    }\n  }\n\n  // Append any remaining elements from each sides.\n  mergedResult.push(...left.slice(l), ...right.slice(r));\n  return mergedResult;\n}\n`;var c=`export default function mergeSort(arr: Array<number>): Array<number> {\n  // Return if array only has 0 or 1 elements (base case).\n  if (arr.length <= 1) {\n    return arr;\n  }\n\n  // Divide the array into two.\n  const midPoint = Math.floor(arr.length / 2);\n  const left = arr.slice(0, midPoint);\n  const right = arr.slice(midPoint);\n\n  // Merge sort each half recursively.\n  const sortedLeft = mergeSort(left);\n  const sortedRight = mergeSort(right);\n\n  // Merge sorted halves.\n  return merge(sortedLeft, sortedRight);\n}\n\n/**\n * Merges two sorted arrays of elements into one.\n */\nfunction merge(left: Array<number>, right: Array<number>): Array<number> {\n  // Create an empty array to store the merged result.\n  const mergedResult = [];\n\n  let l = 0;\n  let r = 0;\n  // Repeatedly compare smallest element from each half\n  // and append it to the merged result.\n  // When one half runs out of elements,\n  // append all the elements of the remaining half to the merged array\n  while (l < left.length && r < right.length) {\n    if (left[l] < right[r]) {\n      mergedResult.push(left[l]);\n      l++;\n    } else {\n      mergedResult.push(right[r]);\n      r++;\n    }\n  }\n\n  // Append any remaining elements from each sides.\n  mergedResult.push(...left.slice(l), ...right.slice(r));\n  return mergedResult;\n}\n`;function g(t){let e=Object.assign({p:\"p\",h2:\"h2\",ul:\"ul\",li:\"li\",h3:\"h3\"},t.components);return(0,r.jsxs)(r.Fragment,{children:[(0,r.jsx)(e.p,{children:\"Merge sort is a stable comparison-based algorithm, with a time complexity of O(nlog(n)) in all cases. It is commonly used in practice as a general-purpose algorithm for sorting arrays of all sizes.\"}),`\n`,(0,r.jsx)(e.h2,{children:\"Clarification questions\"}),`\n`,(0,r.jsx)(e.p,{children:\"If unspecified:\"}),`\n`,(0,r.jsxs)(e.ul,{children:[`\n`,(0,r.jsx)(e.li,{children:\"Should the data be sorted in an ascending or descending order?\"}),`\n`,(0,r.jsx)(e.li,{children:\"Should the data be sorted in-place or is it acceptable to use additional data structures?\"}),`\n`,(0,r.jsxs)(e.li,{children:[\"What kinds of inputs do we need to handle?\",`\n`,(0,r.jsxs)(e.ul,{children:[`\n`,(0,r.jsx)(e.li,{children:\"Will it just be an array of integers or should we handle other data types?\"}),`\n`,(0,r.jsx)(e.li,{children:\"Are there a large number of duplicate elements?\"}),`\n`,(0,r.jsx)(e.li,{children:\"How should negative numbers be handled?\"}),`\n`]}),`\n`]}),`\n`]}),`\n`,(0,r.jsx)(e.h2,{children:\"Solution\"}),`\n`,(0,r.jsx)(e.p,{children:'Note: This question tackles a standard merge sort which is recursive and not \"in-place\" for an output in ascending order.'}),`\n`,(0,r.jsx)(d,{languages:{jsx:m,tsx:c}}),`\n`,(0,r.jsx)(e.h2,{children:\"Edge cases\"}),`\n`,(0,r.jsxs)(e.ul,{children:[`\n`,(0,r.jsx)(e.li,{children:\"Non-integer element input: If the input array comprises of elements of different data types, you may need to return an error, settle for sorting on a best-effort basis, for e.g., only sorting a subset of the input data, or even define custom comparison functions for non-integers.\"}),`\n`,(0,r.jsx)(e.li,{children:\"Single element / Empty input: Either return the original data structure, raise an error, or clarify required handling.\"}),`\n`,(0,r.jsx)(e.li,{children:\"Already sorted input: You may want to detect sorting and return the input unchanged.\"}),`\n`,(0,r.jsx)(e.li,{children:\"Invalid input: If the input is not an array, consider throwing an error.\"}),`\n`]}),`\n`,(0,r.jsx)(e.h2,{children:\"Big-O analysis\"}),`\n`,(0,r.jsx)(e.p,{children:\"Let's analyze the algorithm's time and space complexity.\"}),`\n`,(0,r.jsx)(e.h3,{children:\"Time complexity\"}),`\n`,(0,r.jsx)(e.p,{children:\"In the case of merge sort, the best, average and worst case time complexity are all O(nlog(n)). This means that the time taken for sorting is directly proportional to the product of the array size and logarithm of array size.\"}),`\n`,(0,r.jsx)(e.p,{children:\"The dividing step has a time complexity proportional to the height of the binary tree created due to repeated divisions of the input array in half, and the number of steps is log(n) + 1 at most. Finding the middle of any subarray is a single-step operation that costs O(1). Hence, we expect a time complexity of O(log(n)) for this.\"}),`\n`,(0,r.jsx)(e.p,{children:\"The merging step takes O(n) time for each subarray created by division, as it requires combining of n elements into a single sorted list.\"}),`\n`,(0,r.jsx)(e.p,{children:\"Overall, the time complexity of merge sort is n(log(n) + 1) = O(nlog(n)).\"}),`\n`,(0,r.jsx)(e.h3,{children:\"Space complexity\"}),`\n`,(0,r.jsx)(e.p,{children:\"In terms of space complexity, it is O(n) for a standard merge sort that is recursive and not in-place. The merge step requires the creation of a new array to store the merged result of the 2 halves. At the very last merge step, we expect the array to be as large as the input array. Hence, the space requirement is linear.\"})]})}function S(t={}){let{wrapper:e}=t.components||{};return e?(0,r.jsx)(e,Object.assign({},t,{children:(0,r.jsx)(g,t)})):g(t)}var O=S;return R(j);})();\n;return Component;",
  "workspace": {
    "main": "/src/merge-sort.ts",
    "run": "/src/merge-sort.run.test.ts",
    "submit": "/src/merge-sort.submit.test.ts"
  }
}